Workbook
Name DvListSource1: [1]Sheet2!$B$1:$B$57
Name DvListSource10: [1]Sheet2!$AJ$1:$AJ$27
Name DvListSource11: [1]Sheet2!$AK$1:$AK$5574
Name DvListSource12: [1]Sheet2!$AP$1:$AP$6
Name DvListSource2: [1]Sheet2!$D$1:$D$7
Name DvListSource3: [1]Sheet2!$Z$1:$Z$4
Name DvListSource4: [1]Sheet2!$AA$1:$AA$6
Name DvListSource5: [1]Sheet2!$AE$1:$AE$16
Name DvListSource6: [1]Sheet2!$AF$1:$AF$10
Name DvListSource7: [1]Sheet2!$AG$1
Name DvListSource8: [1]Sheet2!$AH$1
Name DvListSource9: [1]Sheet2!$AI$1:$AI$54

Sheet BASE RECEBIMENTOS
A1: Tipo de doc | B1: Empresa | C1: Código do cliente/fornecedor | D1: Fornecedor | E1: Item do FLuxo de Caixa | F1: Data de Lançamento | G1: Data do Documento | H1: N° da Nota Fiscal | I1: Data do Vencimento | J1: Parcela | K1: Total faltando | L1: DataPg | M1: Juros/Desconto | N1: Total Recebido | O1: Tipo | P1: Nome da Conta | Q1: Observação do lançamento | R1: Criado mediante execução do pagamento | S1: =IF(C1="","",_xlfn.IFNA(_xlfn.XLOOKUP(C1,'CADASTRO CLIENTE'!$B$2:$B$9815,'CADASTRO CLIENTE'!$C$2:$C$9815),"NÃO ENCONTRADO")) -> NÃO ENCONTRADO
A2: NS | B2: KROMA COMERCIALIZADORA DE ENERGIA LTDA | C2: C01145 | D2: INDRA COMERCIALIZADORA DE ENERGIAS LIMITADA | F2: 46301 | G2: 46301 | H2: 51696 | I2: 46303 | J2: 46023 | K2: 0 | L2: 46303 | M2: 0 | N2: 121119.84 | O2: Transferencia | P2: (C) BANCO BRADESCO AG. 2960-2 C/ 116071-0 | Q2: REF RECEB - CR: 4559 - NF: 51696 - PN: INDRA COMERCIALIZADORA DE ENERGIAS LIMITADA | R2: Recebido | S2: =IF(C2="","",_xlfn.IFNA(_xlfn.XLOOKUP(C2,'CADASTRO CLIENTE'!$B$2:$B$9815,'CADASTRO CLIENTE'!$C$2:$C$9815),"NÃO ENCONTRADO")) -> INDRA COMERCIALIZADORA
A3: LC | B3: KROMA COMERCIALIZADORA DE ENERGIA LTDA | C3: C03174 | D3: BRADESCO COMERCIALIZADORA DE ENERGIA LTDA. | K3: 0 | L3: 46234 | M3: 0 | N3: 62004797 | O3: Transferencia | P3: (T) BANCO BRADESCO AG. 2960-2 C/ 116071-0 | Q3: REF RECEB - CR: 959 - LC: 2972 - PN: BRADESCO COMERCIALIZADORA DE ENERGIA LTDA. | R3: Recebido | S3: =IF(C3="","",_xlfn.IFNA(_xlfn.XLOOKUP(C3,'CADASTRO CLIENTE'!$B$2:$B$9815,'CADASTRO CLIENTE'!$C$2:$C$9815),"NÃO ENCONTRADO")) -> BRADESCO COMERCIALIZADORA
A4: NS | B4: KROMA COMERCIALIZADORA DE ENERGIA LTDA | C4: C01767 | D4: CONDOMINIO DO EDIFICIO EMPRESARIAL JMF E JQM | F4: 46244 | G4: 46244 | H4: 50107 | I4: 46244 | J4: 46023 | K4: 0 | L4: 46244 | M4: 0 | N4: 185542.34 | O4: Transferencia | P4: (C) BANCO BRADESCO AG. 2960-2 C/ 116071-0 | Q4: REF RECEB - CR: 1119 - NF: 50107 - PN: CONDOMINIO DO EDIFICIO EMPRESARIAL JMF E JQM | R4: Recebido | S4: =IF(C4="","",_xlfn.IFNA(_xlfn.XLOOKUP(C4,'CADASTRO CLIENTE'!$B$2:$B$9815,'CADASTRO CLIENTE'!$C$2:$C$9815),"NÃO ENCONTRADO")) -> CONDOMÍNIO JMF E JQM
A5: NS | B5: KROMA GESTAO E SERVICOS EM ENERGIA ELETRICA LTDA - EPP | C5: C02950 | D5: TABATINGA AQUACULTURA LTDA | F5: 46267 | G5: 46267 | H5: 1122 | I5: 46295 | J5: 46023 | K5: 0 | L5: 46281 | M5: 0 | N5: 938.5 | O5: Transferencia | P5: (C) BANCO BRADESCO AG. 2960-2 C/ 225-9 | Q5: REF RECEB - CR: 3748 - NF: 1122 - PN: TABATINGA AQUACULTURA LTDA | R5: Recebido | S5: =IF(C5="","",_xlfn.IFNA(_xlfn.XLOOKUP(C5,'CADASTRO CLIENTE'!$B$2:$B$9815,'CADASTRO CLIENTE'!$C$2:$C$9815),"NÃO ENCONTRADO")) -> TABATINGA AQUACULTURA
A6: LC | B6: KROMA GESTAO E SERVICOS EM ENERGIA ELETRICA LTDA - EPP | C6: C02446 | D6: OK DOUTOR CONSULTORIOS MEDICOS LTDA. | K6: 0 | L6: 46204 | M6: 0 | N6: 502.27 | O6: Transferencia | P6: (C) BANCO BRADESCO AG. 2960-2 C/ 225-9 | Q6: REF RECEB - CR: 2112 - LC: 12409 - PN: OK DOUTOR CONSULTORIOS MEDICOS LTDA. | R6: Recebido | S6: =IF(C6="","",_xlfn.IFNA(_xlfn.XLOOKUP(C6,'CADASTRO CLIENTE'!$B$2:$B$9815,'CADASTRO CLIENTE'!$C$2:$C$9815),"NÃO ENCONTRADO")) -> OK DOUTOR CONSULTORIOS MEDICOS
A7: NS | B7: FILIAL - CE - KROMA COMERCIALIZADORA DE ENERGIA LTDA | C7: C01421 | D7: SUPERMERCADO COMETA LTDA | F7: 46239 | G7: 46239 | H7: 1117 | I7: 46244 | J7: 46023 | K7: 0 | L7: 46244 | M7: 0 | N7: 16696.85 | O7: Transferencia | P7: (C) BANCO BRADESCO AG. 2960 C/ 3222-0 | Q7: REF RECEB - CR: 1335 - NF: 1117 - PN: SUPERMERCADO COMETA LTDA | R7: Recebido | S7: =IF(C7="","",_xlfn.IFNA(_xlfn.XLOOKUP(C7,'CADASTRO CLIENTE'!$B$2:$B$9815,'CADASTRO CLIENTE'!$C$2:$C$9815),"NÃO ENCONTRADO")) -> COMETA - VILA PERY (LOJA 23)
A8: NS | B8: KROMA COMERCIALIZADORA DE ENERGIA LTDA | C8: C00909 | D8: SER EDUCACIONAL S.A. | F8: 46261 | G8: 46261 | H8: 2026082701 | I8: 46268 | J8: 46023 | K8: 0 | L8: 46267 | M8: 0 | N8: 515.16 | O8: Transferencia | P8: (C) BANCO BRADESCO AG. 2960-2 C/ 116071-0 | Q8: REF RECEB - CR: 2845 - NF: 2026082701 - PN: SER EDUCACIONAL S.A. | R8: Recebido | S8: =IF(C8="","",_xlfn.IFNA(_xlfn.XLOOKUP(C8,'CADASTRO CLIENTE'!$B$2:$B$9815,'CADASTRO CLIENTE'!$C$2:$C$9815),"NÃO ENCONTRADO")) -> SER - GRAÇAS
A9: NS | B9: SAO PEDRO E PAULO I SPE SA | C9: C03372 | D9: ENERGISA MATO GROSSO DO SUL - DISTRIBUIDORA DE ENERGIA S.A. | F9: 46209 | G9: 46209 | H9: 1446 | I9: 46218 | J9: 46023 | K9: 0 | L9: 46218 | M9: 0 | N9: 12317.29 | O9: Transferencia | P9: (C) BANCO BRADESCO AG. 2960 C/C 219-4 | Q9: REF RECEB - CR: 877 - NF: 1446 - PN: ENERGISA MATO GROSSO DO SUL - DISTRIBUIDORA DE ENERGIA S.A. | R9: Recebido | S9: =IF(C9="","",_xlfn.IFNA(_xlfn.XLOOKUP(C9,'CADASTRO CLIENTE'!$B$2:$B$9815,'CADASTRO CLIENTE'!$C$2:$C$9815),"NÃO ENCONTRADO")) -> ENERGISA MS
A10: NS | B10: KROMA COMERCIALIZADORA DE ENERGIA LTDA | C10: C02228 | D10: APEL ATIVIDADES PRO ENSINO LTDA | F10: 46206 | G10: 46206 | H10: 48728 | I10: 46211 | J10: 46023 | K10: 0 | L10: 46210 | M10: 0 | N10: 1556.16 | O10: Transferencia | P10: (C) BANCO BRADESCO AG. 2960-2 C/ 116071-0 | Q10: REF RECEB - CR: 259 - NF: 48728 - PN: APEL ATIVIDADES PRO ENSINO LTDA | R10: Recebido | S10: =IF(C10="","",_xlfn.IFNA(_xlfn.XLOOKUP(C10,'CADASTRO CLIENTE'!$B$2:$B$9815,'CADASTRO CLIENTE'!$C$2:$C$9815),"NÃO ENCONTRADO")) -> COLEGIO CHRISTUS - SIL. PAULET
A11: NS | B11: KROMA COMERCIALIZADORA DE ENERGIA LTDA | C11: C00109 | D11: CEMIG GERACAO E TRANSMISSAO S.A | F11: 46237 | G11: 46237 | H11: 49423 | I11: 46244 | J11: 46023 | K11: 0 | L11: 46244 | M11: 0 | N11: 766989.6 | O11: Transferencia | P11: (C) BANCO BRADESCO AG. 2960-2 C/ 116071-0 | Q11: REF RECEB - CR: 1320 - NF: 49423 - PN: CEMIG GERACAO E TRANSMISSAO S.A | R11: Recebido | S11: =IF(C11="","",_xlfn.IFNA(_xlfn.XLOOKUP(C11,'CADASTRO CLIENTE'!$B$2:$B$9815,'CADASTRO CLIENTE'!$C$2:$C$9815),"NÃO ENCONTRADO")) -> CEMIG
A12: NS | B12: UFV FLIP PRATA SPE S.A. | C12: C03466 | D12: GISELDA MARIA TORREAS DA LUZ | F12: 46252 | G12: 46252 | H12: 133 | I12: 46252 | J12: 46023 | K12: 0 | L12: 46308 | M12: 0 | N12: 355.66 | O12: Transferencia | P12: (C) BANCO BRADESCO AG 2960 CC 3193-3 | Q12: REF RECEB - CR: 5256 - NF: 133 - PN: GISELDA MARIA TORREAS DA LUZ | R12: Recebido | S12: =IF(C12="","",_xlfn.IFNA(_xlfn.XLOOKUP(C12,'CADASTRO CLIENTE'!$B$2:$B$9815,'CADASTRO CLIENTE'!$C$2:$C$9815),"NÃO ENCONTRADO")) -> 0
A13: NS | B13: KROMA COMERCIALIZADORA DE ENERGIA LTDA | C13: C03392 | D13: SERVICO NACIONAL DE APRENDIZAGEM INDUSTRIAL | F13: 46206 | G13: 46206 | H13: 48654 | I13: 46211 | J13: 46023 | K13: 0 | L13: 46211 | M13: 0 | N13: 2704.02 | O13: Transferencia | P13: (C) BANCO BRADESCO AG. 2960-2 C/ 116071-0 | Q13: REF RECEB - CR: 24 - NF: 48654 - PN: SERVICO NACIONAL DE APRENDIZAGEM INDUSTRIAL | R13: Recebido | S13: =IF(C13="","",_xlfn.IFNA(_xlfn.XLOOKUP(C13,'CADASTRO CLIENTE'!$B$2:$B$9815,'CADASTRO CLIENTE'!$C$2:$C$9815),"NÃO ENCONTRADO")) -> SENAI ARARIPINA
A14: LC | B14: KROMA GESTAO E SERVICOS EM ENERGIA ELETRICA LTDA - EPP | C14: C02271 | D14: UNIAO DE PROFESSORES LTDA | K14: 0 | L14: 46204 | M14: 0 | N14: 716.5 | O14: Transferencia | P14: (C) BANCO BRADESCO AG. 2960-2 C/ 225-9 | Q14: REF RECEB - CR: 2082 - LC: 12366 - PN: UNIAO DE PROFESSORES LTDA | R14: Recebido | S14: =IF(C14="","",_xlfn.IFNA(_xlfn.XLOOKUP(C14,'CADASTRO CLIENTE'!$B$2:$B$9815,'CADASTRO CLIENTE'!$C$2:$C$9815),"NÃO ENCONTRADO")) -> UP - VILA VELHA
A15: NS | B15: KROMA COMERCIALIZADORA DE ENERGIA LTDA | C15: C02943 | D15: BONANZA SUPERMERCADOS LTDA EM RECUPERACAO JUDICIAL | F15: 46302 | G15: 46302 | H15: 51860 | I15: 46307 | J15: 46023 | K15: 0 | L15: 46308 | M15: 0 | N15: 12507.16 | O15: Transferencia | P15: (C) BANCO BNB AG. 44 C/ 49680-0 | Q15: REF RECEB - CR: 4875 - NF: 51860 - PN: BONANZA SUPERMERCADOS LTDA EM RECUPERACAO JUDICIAL | R15: Recebido | S15: =IF(C15="","",_xlfn.IFNA(_xlfn.XLOOKUP(C15,'CADASTRO CLIENTE'!$B$2:$B$9815,'CADASTRO CLIENTE'!$C$2:$C$9815),"NÃO ENCONTRADO")) -> BONANZA - LOJA 02
A16: NS | B16: KROMA COMERCIALIZADORA DE ENERGIA LTDA | C16: C02536 | D16: SELF IT ACADEMIAS HOLDING S.A. | F16: 46239 | G16: 46239 | H16: 49803 | I16: 46248 | J16: 46023 | K16: 0 | L16: 46244 | M16: 0 | N16: 7183.83 | O16: Transferencia | P16: (C) BANCO BRADESCO AG. 2960-2 C/ 116071-0 | Q16: REF RECEB - CR: 1212 - NF: 49803 - PN: SELF IT ACADEMIAS HOLDING S.A. | R16: Recebido | S16: =IF(C16="","",_xlfn.IFNA(_xlfn.XLOOKUP(C16,'CADASTRO CLIENTE'!$B$2:$B$9815,'CADASTRO CLIENTE'!$C$2:$C$9815),"NÃO ENCONTRADO")) -> SELFIT DIRCEU (PI)
A17: NS | B17: KROMA COMERCIALIZADORA DE ENERGIA LTDA | C17: C02538 | D17: ASSUPERO ENSINO SUPERIOR LTDA. | F17: 46300 | G17: 46300 | H17: 51458 | I17: 46310 | J17: 46023 | K17: 0 | L17: 46304 | M17: 0 | N17: 26898.12 | O17: Transferencia | P17: (C) BANCO BRADESCO AG. 2960-2 C/ 116071-0 | Q17: REF RECEB - CR: 4731 - NF: 51458 - PN: ASSUPERO ENSINO SUPERIOR LTDA. | R17: Recebido | S17: =IF(C17="","",_xlfn.IFNA(_xlfn.XLOOKUP(C17,'CADASTRO CLIENTE'!$B$2:$B$9815,'CADASTRO CLIENTE'!$C$2:$C$9815),"NÃO ENCONTRADO")) -> UNIP TERESINA
A18: NS | B18: KROMA COMERCIALIZADORA DE ENERGIA LTDA | C18: C02704 | D18: SOCIEDADE EDUCACIONAL JABAQUARA LTDA. | F18: 46239 | G18: 46239 | H18: 49837 | I18: 46249 | J18: 46023 | K18: 0 | L18: 46251 | M18: 0 | N18: 808.36 | O18: Transferencia | P18: (C) BANCO BRADESCO AG. 2960-2 C/ 116071-0 | Q18: REF RECEB - CR: 1746 - NF: 49837 - PN: SOCIEDADE EDUCACIONAL JABAQUARA LTDA. | R18: Recebido | S18: =IF(C18="","",_xlfn.IFNA(_xlfn.XLOOKUP(C18,'CADASTRO CLIENTE'!$B$2:$B$9815,'CADASTRO CLIENTE'!$C$2:$C$9815),"NÃO ENCONTRADO")) -> INSPIRA - MTE0004324
A19: NS | B19: KROMA COMERCIALIZADORA DE ENERGIA LTDA | C19: C01494 | D19: DUCOCO PRODUTOS ALIMENTICIOS S/A | F19: 46269 | G19: 46269 | H19: 50803 | I19: 46273 | J19: 46023 | K19: 0 | L19: 46274 | M19: 0 | N19: 548788.69 | O19: Transferencia | P19: (C) BANCO BNB AG. 44 C/ 49680-0 | Q19: REF RECEB - CR: 3094 - NF: 50803 - PN: DUCOCO PRODUTOS ALIMENTICIOS S/A | R19: Recebido | S19: =IF(C19="","",_xlfn.IFNA(_xlfn.XLOOKUP(C19,'CADASTRO CLIENTE'!$B$2:$B$9815,'CADASTRO CLIENTE'!$C$2:$C$9815),"NÃO ENCONTRADO")) -> DUCOCO
A20: NS | B20: KROMA COMERCIALIZADORA DE ENERGIA LTDA | C20: C02234 | D20: FORPACK INDUSTRIA DE EMBALAGENS LTDA | F20: 46206 | G20: 46206 | H20: 48618 | I20: 46211 | J20: 46023 | K20: 0 | L20: 46210 | M20: 0 | N20: 12139.93 | O20: Transferencia | P20: (C) BANCO BRADESCO AG. 2960-2 C/ 116071-0 | Q20: REF RECEB - CR: 266 - NF: 48618 - PN: FORPACK INDUSTRIA DE EMBALAGENS LTDA | R20: Recebido | S20: =IF(C20="","",_xlfn.IFNA(_xlfn.XLOOKUP(C20,'CADASTRO CLIENTE'!$B$2:$B$9815,'CADASTRO CLIENTE'!$C$2:$C$9815),"NÃO ENCONTRADO")) -> FORPACK
A21: LC | B21: KROMA COMERCIALIZADORA DE ENERGIA LTDA | C21: C02118 | D21: COMANDO DA MARINHA | K21: 0 | L21: 46234 | M21: 0 | N21: 6221 | O21: Transferencia | P21: (T) BANCO BRADESCO AG. 2960-2 C/ 116071-0 | Q21: REF RECEB - CR: 968 - LC: 2972 - PN: COMANDO DA MARINHA | R21: Recebido | S21: =IF(C21="","",_xlfn.IFNA(_xlfn.XLOOKUP(C21,'CADASTRO CLIENTE'!$B$2:$B$9815,'CADASTRO CLIENTE'!$C$2:$C$9815),"NÃO ENCONTRADO")) -> HNSA
A22: LC | B22: KROMA COMERCIALIZADORA DE ENERGIA LTDA | C22: C02558 | D22: GALPAO TROPEIRO CHURRASCARIA LTDA | K22: 0 | L22: 46205 | M22: 144.73 | N22: 7220.53 | O22: Transferencia | P22: (C) BANCO BRADESCO AG. 2960-2 C/ 116071-0 | Q22: REF RECEB - CR: 314 - LC: 2972 - PN: GALPAO TROPEIRO CHURRASCARIA LTDA | R22: Recebido | S22: =IF(C22="","",_xlfn.IFNA(_xlfn.XLOOKUP(C22,'CADASTRO CLIENTE'!$B$2:$B$9815,'CADASTRO CLIENTE'!$C$2:$C$9815),"NÃO ENCONTRADO")) -> GALPAO TROPEIRO
A23: NS | B23: KROMA COMERCIALIZADORA DE ENERGIA LTDA | C23: C01644 | D23: BCI COMERCIALIZADORA LTDA | F23: 46205 | G23: 46205 | H23: 48338 | I23: 46218 | J23: 46023 | K23: 0 | L23: 46227 | M23: 0 | N23: 3192.3 | O23: Transferencia | P23: (C) BANCO BRADESCO AG. 2960-2 C/ 116071-0 | Q23: REF RECEB - CR: 844 - NF: 48338 - PN: BCI COMERCIALIZADORA LTDA | R23: Recebido | S23: =IF(C23="","",_xlfn.IFNA(_xlfn.XLOOKUP(C23,'CADASTRO CLIENTE'!$B$2:$B$9815,'CADASTRO CLIENTE'!$C$2:$C$9815),"NÃO ENCONTRADO")) -> BCI
A24: NS | B24: KROMA COMERCIALIZADORA DE ENERGIA LTDA | C24: C01592 | D24: JP STEAK HOUSE CUIABA BUFFET E RESTAURANTE LTDA | F24: 46206 | G24: 46206 | H24: 48470 | I24: 46218 | J24: 46023 | K24: 0 | L24: 46237 | M24: 136.94 | N24: 5630.42 | O24: Transferencia | P24: (C) BANCO BRADESCO AG. 2960-2 C/ 116071-0 | Q24: REF RECEB - CR: 938 - NF: 48470 - PN: JP STEAK HOUSE CUIABA BUFFET E RESTAURANTE LTDA | R24: Recebido | S24: =IF(C24="","",_xlfn.IFNA(_xlfn.XLOOKUP(C24,'CADASTRO CLIENTE'!$B$2:$B$9815,'CADASTRO CLIENTE'!$C$2:$C$9815),"NÃO ENCONTRADO")) -> FAVO DE MEL
A25: LC | B25: KROMA COMERCIALIZADORA DE ENERGIA LTDA | C25: C02809 | D25: ARAPUA II SPE S.A. | K25: 0 | L25: 46234 | M25: 0 | N25: 5000000 | O25: Transferencia | P25: (T) BANCO BRADESCO AG. 2960-2 C/ 116071-0 | Q25: REF RECEB - CR: 950 - LC: 2972 - PN: ARAPUA II SPE S.A. | R25: Recebido | S25: =IF(C25="","",_xlfn.IFNA(_xlfn.XLOOKUP(C25,'CADASTRO CLIENTE'!$B$2:$B$9815,'CADASTRO CLIENTE'!$C$2:$C$9815),"NÃO ENCONTRADO")) -> ARAPUA II SPE
A26: NS | B26: KROMA COMERCIALIZADORA DE ENERGIA LTDA | C26: C02882 | D26: INSPIRA NORTE PARTICIPACOES S/A | F26: 46239 | G26: 46239 | H26: 49867 | I26: 46249 | J26: 46023 | K26: 0 | L26: 46251 | M26: 0 | N26: 5312.8 | O26: Transferencia | P26: (C) BANCO BRADESCO AG. 2960-2 C/ 116071-0 | Q26: REF RECEB - CR: 1798 - NF: 49867 - PN: INSPIRA NORTE PARTICIPACOES S/A | R26: Recebido | S26: =IF(C26="","",_xlfn.IFNA(_xlfn.XLOOKUP(C26,'CADASTRO CLIENTE'!$B$2:$B$9815,'CADASTRO CLIENTE'!$C$2:$C$9815),"NÃO ENCONTRADO")) -> REDE INSPIRA UC COD 43
A27: NS | B27: KROMA COMERCIALIZADORA DE ENERGIA LTDA | C27: C01767 | D27: CONDOMINIO DO EDIFICIO EMPRESARIAL JMF E JQM | F27: 46213 | G27: 46213 | H27: 49244 | I27: 46213 | J27: 46023 | K27: 0 | L27: 46213 | M27: 0 | N27: 176226.29 | O27: Transferencia | P27: (C) BANCO BRADESCO AG. 2960-2 C/ 116071-0 | Q27: REF RECEB - CR: 200 - NF: 49244 - PN: CONDOMINIO DO EDIFICIO EMPRESARIAL JMF E JQM | R27: Recebido | S27: =IF(C27="","",_xlfn.IFNA(_xlfn.XLOOKUP(C27,'CADASTRO CLIENTE'!$B$2:$B$9815,'CADASTRO CLIENTE'!$C$2:$C$9815),"NÃO ENCONTRADO")) -> CONDOMÍNIO JMF E JQM
A28: LC | B28: KROMA GESTAO E SERVICOS EM ENERGIA ELETRICA LTDA - EPP | C28: C01739 | D28: RUI BARBOSA DELICATESSEN COMERCIO DE ALIMENTOS LTDA | K28: 0 | L28: 46279 | M28: 0 | N28: 603.73 | O28: Transferencia | P28: (C) BANCO BRADESCO AG. 2960-2 C/ 225-9 | Q28: REF RECEB - CR: 3403 - LC: 11980 - PN: RUI BARBOSA DELICATESSEN COMERCIO DE ALIMENTOS LTDA | R28: Recebido | S28: =IF(C28="","",_xlfn.IFNA(_xlfn.XLOOKUP(C28,'CADASTRO CLIENTE'!$B$2:$B$9815,'CADASTRO CLIENTE'!$C$2:$C$9815),"NÃO ENCONTRADO")) -> RUI BARBOSA DELICATESSEN
A29: NS | B29: KROMA COMERCIALIZADORA DE ENERGIA LTDA | C29: C01813 | D29: SELF IT ACADEMIAS HOLDING S.A. | F29: 46239 | G29: 46239 | H29: 49795 | I29: 46248 | J29: 46023 | K29: 0 | L29: 46244 | M29: 0 | N29: 7437.9 | O29: Transferencia | P29: (C) BANCO BRADESCO AG. 2960-2 C/ 116071-0 | Q29: REF RECEB - CR: 1215 - NF: 49795 - PN: SELF IT ACADEMIAS HOLDING S.A. | R29: Recebido | S29: =IF(C29="","",_xlfn.IFNA(_xlfn.XLOOKUP(C29,'CADASTRO CLIENTE'!$B$2:$B$9815,'CADASTRO CLIENTE'!$C$2:$C$9815),"NÃO ENCONTRADO")) -> SELF IT - P KENNEDY
A30: NS | B30: KROMA COMERCIALIZADORA DE ENERGIA LTDA | C30: C03128 | D30: HOSPITAL VETERINARIO DOK LTDA | F30: 46300 | G30: 46300 | H30: 51489 | I30: 46314 | J30: 46023 | K30: 0 | L30: 46314 | M30: 0 | N30: 965.57 | O30: Transferencia | P30: (C) BANCO BRADESCO AG. 2960-2 C/ 116071-0 | Q30: REF RECEB - CR: 5246 - NF: 51489 - PN: HOSPITAL VETERINARIO DOK LTDA | R30: Recebido | S30: =IF(C30="","",_xlfn.IFNA(_xlfn.XLOOKUP(C30,'CADASTRO CLIENTE'!$B$2:$B$9815,'CADASTRO CLIENTE'!$C$2:$C$9815),"NÃO ENCONTRADO")) -> SER - DOK HOVET GUARULHOS
A31: NS | B31: KROMA COMERCIALIZADORA DE ENERGIA LTDA | C31: C02305 | D31: CNS - CENTRAL DE NUCLEOS SILICIOSOS LTDA | F31: 46237 | G31: 46237 | H31: 49416 | I31: 46249 | J31: 46023 | K31: 0 | L31: 46247 | M31: 0 | N31: 28646.46 | O31: Transferencia | P31: (C) BANCO BRADESCO AG. 2960-2 C/ 116071-0 | Q31: REF RECEB - CR: 1478 - NF: 49416 - PN: CNS - CENTRAL DE NUCLEOS SILICIOSOS LTDA | R31: Recebido | S31: =IF(C31="","",_xlfn.IFNA(_xlfn.XLOOKUP(C31,'CADASTRO CLIENTE'!$B$2:$B$9815,'CADASTRO CLIENTE'!$C$2:$C$9815),"NÃO ENCONTRADO")) -> CNS
A32: NS | B32: KROMA COMERCIALIZADORA DE ENERGIA LTDA | C32: C00873 | D32: MAC 01 - COMERCIALIZADORA DE ENERGIA LTDA | F32: 46237 | G32: 46237 | H32: 49420 | I32: 46244 | J32: 46023 | K32: 0 | L32: 46244 | M32: 0 | N32: 21254 | O32: Transferencia | P32: (C) BANCO BRADESCO AG. 2960-2 C/ 116071-0 | Q32: REF RECEB - CR: 1136 - NF: 49420 - PN: MAC 01 - COMERCIALIZADORA DE ENERGIA LTDA | R32: Recebido | S32: =IF(C32="","",_xlfn.IFNA(_xlfn.XLOOKUP(C32,'CADASTRO CLIENTE'!$B$2:$B$9815,'CADASTRO CLIENTE'!$C$2:$C$9815),"NÃO ENCONTRADO")) -> GOE COMERCIALIZADORA
A33: NS | B33: KROMA COMERCIALIZADORA DE ENERGIA LTDA | C33: C02238 | D33: TREVO INDUSTRIAL DE ACARTONADOS S/A | F33: 46296 | G33: 46296 | H33: 51167 | I33: 46303 | J33: 46023 | K33: 0 | L33: 46303 | M33: 0 | N33: 175909.74 | O33: Transferencia | P33: (C) BANCO BRADESCO AG. 2960-2 C/ 116071-0 | Q33: REF RECEB - CR: 4563 - NF: 51167 - PN: TREVO INDUSTRIAL DE ACARTONADOS S/A | R33: Recebido | S33: =IF(C33="","",_xlfn.IFNA(_xlfn.XLOOKUP(C33,'CADASTRO CLIENTE'!$B$2:$B$9815,'CADASTRO CLIENTE'!$C$2:$C$9815),"NÃO ENCONTRADO")) -> TREVO
A34: LC | B34: KROMA GESTAO E SERVICOS EM ENERGIA ELETRICA LTDA - EPP | C34: C02324 | D34: CONDOMINIO TORRE DOMANI | K34: 0 | L34: 46220 | M34: 0 | N34: 238.37 | O34: Transferencia | P34: (C) BANCO BRADESCO AG. 2960-2 C/ 225-9 | Q34: REF RECEB - CR: 2313 - LC: 11849 - PN: CONDOMINIO TORRE DOMANI | R34: Recebido | S34: =IF(C34="","",_xlfn.IFNA(_xlfn.XLOOKUP(C34,'CADASTRO CLIENTE'!$B$2:$B$9815,'CADASTRO CLIENTE'!$C$2:$C$9815),"NÃO ENCONTRADO")) -> DOMANI
A35: NS | B35: KROMA COMERCIALIZADORA DE ENERGIA LTDA | C35: C03064 | D35: INSPIRA NORTE PARTICIPACOES S/A | F35: 46210 | G35: 46210 | H35: 49028 | I35: 46218 | J35: 46023 | K35: 0 | L35: 46218 | M35: 0 | N35: 4155.8 | O35: Transferencia | P35: (C) BANCO BRADESCO AG. 2960-2 C/ 116071-0 | Q35: REF RECEB - CR: 647 - NF: 49028 - PN: INSPIRA NORTE PARTICIPACOES S/A | R35: Recebido | S35: =IF(C35="","",_xlfn.IFNA(_xlfn.XLOOKUP(C35,'CADASTRO CLIENTE'!$B$2:$B$9815,'CADASTRO CLIENTE'!$C$2:$C$9815),"NÃO ENCONTRADO")) -> REDE INSPIRA - UC COD 31
A36: NS | B36: KROMA COMERCIALIZADORA DE ENERGIA LTDA | C36: C02290 | D36: LEANDRO OLIVEIRA ANDRADE SERVICOS LTDA | F36: 46238 | G36: 46238 | H36: 49689 | I36: 46249 | J36: 46023 | K36: 0 | L36: 46253 | M36: 0 | N36: 2882.18 | O36: Transferencia | P36: (C) BANCO BRADESCO AG. 2960-2 C/ 116071-0 | Q36: REF RECEB - CR: 1933 - NF: 49689 - PN: LEANDRO OLIVEIRA ANDRADE SERVICOS LTDA | R36: Recebido | S36: =IF(C36="","",_xlfn.IFNA(_xlfn.XLOOKUP(C36,'CADASTRO CLIENTE'!$B$2:$B$9815,'CADASTRO CLIENTE'!$C$2:$C$9815),"NÃO ENCONTRADO")) -> LEANDRO OLIVEIRA SERVICOS
A37: NS | B37: KROMA GESTAO E SERVICOS EM ENERGIA ELETRICA LTDA - EPP | C37: C02999 | D37: ROTA PREMIUM VEICULOS LTDA | F37: 46267 | G37: 46267 | H37: 1085 | I37: 46295 | J37: 46023 | K37: 0 | L37: 46294 | M37: 0 | N37: 938.5 | O37: Transferencia | P37: (C) BANCO BRADESCO AG. 2960-2 C/ 225-9 | Q37: REF RECEB - CR: 4057 - NF: 1085 - PN: ROTA PREMIUM VEICULOS LTDA | R37: Recebido | S37: =IF(C37="","",_xlfn.IFNA(_xlfn.XLOOKUP(C37,'CADASTRO CLIENTE'!$B$2:$B$9815,'CADASTRO CLIENTE'!$C$2:$C$9815),"NÃO ENCONTRADO")) -> ROTA PREMIUM
A38: NS | B38: KROMA COMERCIALIZADORA DE ENERGIA LTDA | C38: C01640 | D38: BONANZA SUPERMERCADOS LTDA EM RECUPERACAO JUDICIAL | F38: 46302 | G38: 46302 | H38: 51864 | I38: 46307 | J38: 46023 | K38: 0 | L38: 46308 | M38: 0 | N38: 7270.36 | O38: Transferencia | P38: (C) BANCO BNB AG. 44 C/ 49680-0 | Q38: REF RECEB - CR: 4879 - NF: 51864 - PN: BONANZA SUPERMERCADOS LTDA EM RECUPERACAO JUDICIAL | R38: Recebido | S38: =IF(C38="","",_xlfn.IFNA(_xlfn.XLOOKUP(C38,'CADASTRO CLIENTE'!$B$2:$B$9815,'CADASTRO CLIENTE'!$C$2:$C$9815),"NÃO ENCONTRADO")) -> BONANZA SUPERMERCADOS
A39: NS | B39: FILIAL - PB - KROMA COMERCIALIZADORA DE ENERGIA LTDA | C39: C02912 | D39: COMPANHIA DE AGUA E ESGOTOS DA PARAIBA CAGEPA | F39: 46269 | G39: 46269 | H39: 478 | I39: 46285 | J39: 46023 | K39: 0 | L39: 46283 | M39: 0 | N39: 17325.78 | O39: Transferencia | P39: (C) BANCO BRADESCO AG. 2960-2 C/ 116071-0 | Q39: REF RECEB - CR: 3812 - NF: 478 - PN: COMPANHIA DE AGUA E ESGOTOS DA PARAIBA CAGEPA | R39: Recebido | S39: =IF(C39="","",_xlfn.IFNA(_xlfn.XLOOKUP(C39,'CADASTRO CLIENTE'!$B$2:$B$9815,'CADASTRO CLIENTE'!$C$2:$C$9815),"NÃO ENCONTRADO")) -> CAGEPA
A40: NS | B40: KROMA COMERCIALIZADORA DE ENERGIA LTDA | C40: C01654 | D40: PE ENERGIA SPE S/A | F40: 46232 | G40: 46232 | H40: 49337 | I40: 46233 | J40: 46023 | K40: 0 | L40: 46232 | M40: 0 | N40: 3974831.9 | O40: Transferencia | P40: (C) BANCO ABC AG. 1 C/ 2323822-6 | Q40: REF RECEB - CR: 886 - NF: 49337 - PN: PE ENERGIA SPE S/A | R40: Recebido | S40: =IF(C40="","",_xlfn.IFNA(_xlfn.XLOOKUP(C40,'CADASTRO CLIENTE'!$B$2:$B$9815,'CADASTRO CLIENTE'!$C$2:$C$9815),"NÃO ENCONTRADO")) -> PE ENERGIA SPE
A41: NS | B41: KROMA COMERCIALIZADORA DE ENERGIA LTDA | C41: C02064 | D41: EMPRESA CENTERPLEX DE CINEMAS LTDA - EM RECUPERACAO JUDICIAL | F41: 46206 | G41: 46206 | H41: 48742 | I41: 46211 | J41: 46023 | K41: 0 | L41: 46211 | M41: 0 | N41: 22196.71 | O41: Transferencia | P41: (C) BANCO BRADESCO AG. 2960-2 C/ 116071-0 | Q41: REF RECEB - CR: 152 - NF: 48742 - PN: EMPRESA CENTERPLEX DE CINEMAS LTDA - EM RECUPERACAO JUDICIAL | R41: Recebido | S41: =IF(C41="","",_xlfn.IFNA(_xlfn.XLOOKUP(C41,'CADASTRO CLIENTE'!$B$2:$B$9815,'CADASTRO CLIENTE'!$C$2:$C$9815),"NÃO ENCONTRADO")) -> CENTERPLEX - MACEIO
A42: NS | B42: KROMA GESTAO E SERVICOS EM ENERGIA ELETRICA LTDA - EPP | C42: C01456 | D42: TV JANGADEIRO LTDA | F42: 46225 | G42: 46225 | H42: 79 | I42: 46237 | J42: 46023 | K42: 0 | L42: 46237 | M42: 0 | N42: 2935.56 | O42: Transferencia | P42: (C) BANCO BRADESCO AG. 2960-2 C/ 225-9 | Q42: REF RECEB - CR: 2386 - NF: 79 - PN: TV JANGADEIRO LTDA | R42: Recebido | S42: =IF(C42="","",_xlfn.IFNA(_xlfn.XLOOKUP(C42,'CADASTRO CLIENTE'!$B$2:$B$9815,'CADASTRO CLIENTE'!$C$2:$C$9815),"NÃO ENCONTRADO")) -> TV JANGADEIRO
A43: NS | B43: KROMA COMERCIALIZADORA DE ENERGIA LTDA | C43: C03504 | D43: MASTERBOI LTDA. | F43: 46303 | G43: 46303 | H43: 51910 | I43: 46304 | J43: 46023 | K43: 0 | L43: 46308 | M43: 0 | N43: 769.36 | O43: Transferencia | P43: (C) BANCO BRADESCO AG. 2960-2 C/ 116071-0 | Q43: REF RECEB - CR: 4844 - NF: 51910 - PN: MASTERBOI LTDA. | R43: Recebido | S43: =IF(C43="","",_xlfn.IFNA(_xlfn.XLOOKUP(C43,'CADASTRO CLIENTE'!$B$2:$B$9815,'CADASTRO CLIENTE'!$C$2:$C$9815),"NÃO ENCONTRADO")) -> MASTERBOI - CEASA
A44: NS | B44: KROMA COMERCIALIZADORA DE ENERGIA LTDA | C44: C03410 | D44: SERVICO SOCIAL DA INDUSTRIA | F44: 46301 | G44: 46301 | H44: 51583 | I44: 46303 | J44: 46023 | K44: 0 | L44: 46303 | M44: 0 | N44: 6047.92 | O44: Transferencia | P44: (C) BANCO BRADESCO AG. 2960-2 C/ 116071-0 | Q44: REF RECEB - CR: 4515 - NF: 51583 - PN: SERVICO SOCIAL DA INDUSTRIA | R44: Recebido | S44: =IF(C44="","",_xlfn.IFNA(_xlfn.XLOOKUP(C44,'CADASTRO CLIENTE'!$B$2:$B$9815,'CADASTRO CLIENTE'!$C$2:$C$9815),"NÃO ENCONTRADO")) -> SESI SAUDE
A45: NS | B45: KROMA COMERCIALIZADORA DE ENERGIA LTDA | C45: C02536 | D45: SELF IT ACADEMIAS HOLDING S.A. | F45: 46209 | G45: 46209 | H45: 48867 | I45: 46217 | J45: 46023 | K45: 0 | L45: 46218 | M45: 0 | N45: 6631.91 | O45: Transferencia | P45: (C) BANCO BRADESCO AG. 2960-2 C/ 116071-0 | Q45: REF RECEB - CR: 700 - NF: 48867 - PN: SELF IT ACADEMIAS HOLDING S.A. | R45: Recebido | S45: =IF(C45="","",_xlfn.IFNA(_xlfn.XLOOKUP(C45,'CADASTRO CLIENTE'!$B$2:$B$9815,'CADASTRO CLIENTE'!$C$2:$C$9815),"NÃO ENCONTRADO")) -> SELFIT DIRCEU (PI)
A46: NS | B46: KROMA GESTAO E SERVICOS EM ENERGIA ELETRICA LTDA - EPP | C46: C02409 | D46: CENTRO DE TRATAMENTO RENAL ZONA SUL LTDA - EM RECUPERACAO JUDICIAL | F46: 46230 | G46: 46230 | H46: 302 | I46: 46244 | J46: 46023 | K46: 0 | L46: 46246 | M46: 0 | N46: 724.22 | O46: Transferencia | P46: (C) BANCO BRADESCO AG. 2960-2 C/ 225-9 | Q46: REF RECEB - CR: 2796 - NF: 302 - PN: CENTRO DE TRATAMENTO RENAL ZONA SUL LTDA - EM RECUPERACAO JUDICIAL | R46: Recebido | S46: =IF(C46="","",_xlfn.IFNA(_xlfn.XLOOKUP(C46,'CADASTRO CLIENTE'!$B$2:$B$9815,'CADASTRO CLIENTE'!$C$2:$C$9815),"NÃO ENCONTRADO")) -> CT RENAL
A47: LC | B47: KROMA GESTAO E SERVICOS EM ENERGIA ELETRICA LTDA - EPP | C47: C00902 | D47: DSI - EMPREENDIMENTOS LTDA | K47: 0 | L47: 46204 | M47: 0 | N47: 833.61 | O47: Transferencia | P47: (C) BANCO BRADESCO AG. 2960-2 C/ 225-9 | Q47: REF RECEB - CR: 2071 - LC: 12341 - PN: DSI - EMPREENDIMENTOS LTDA | R47: Recebido | S47: =IF(C47="","",_xlfn.IFNA(_xlfn.XLOOKUP(C47,'CADASTRO CLIENTE'!$B$2:$B$9815,'CADASTRO CLIENTE'!$C$2:$C$9815),"NÃO ENCONTRADO")) -> DSI
A48: NS | B48: KROMA COMERCIALIZADORA DE ENERGIA LTDA | C48: C01797 | D48: SUPERMERCADO FENIX LTDA | F48: 46210 | G48: 46210 | H48: 49099 | I48: 46211 | J48: 46023 | K48: 0 | L48: 46213 | M48: 0 | N48: 19572.35 | O48: Transferencia | P48: (C) BANCO BRADESCO AG. 2960-2 C/ 116071-0 | Q48: REF RECEB - CR: 248 - NF: 49099 - PN: SUPERMERCADO FENIX LTDA | R48: Recebido | S48: =IF(C48="","",_xlfn.IFNA(_xlfn.XLOOKUP(C48,'CADASTRO CLIENTE'!$B$2:$B$9815,'CADASTRO CLIENTE'!$C$2:$C$9815),"NÃO ENCONTRADO")) -> FENIX SIRINHAEM
A49: NS | B49: SAO PEDRO E PAULO I SPE SA | C49: C03373 | D49: ENERGISA MATO GROSSO - DISTRIBUIDORA DE ENERGIA S.A. | F49: 46251 | G49: 46251 | H49: 1534 | I49: 46264 | J49: 46023 | K49: 0 | L49: 46265 | M49: 0 | N49: 17118.89 | O49: Transferencia | P49: (C) BANCO BRADESCO AG. 2960 C/C 219-4 | Q49: REF RECEB - CR: 3397 - NF: 1534 - PN: ENERGISA MATO GROSSO - DISTRIBUIDORA DE ENERGIA S.A. | R49: Recebido | S49: =IF(C49="","",_xlfn.IFNA(_xlfn.XLOOKUP(C49,'CADASTRO CLIENTE'!$B$2:$B$9815,'CADASTRO CLIENTE'!$C$2:$C$9815),"NÃO ENCONTRADO")) -> ENERGISA MT
A50: NS | B50: KROMA COMERCIALIZADORA DE ENERGIA LTDA | C50: C01454 | D50: DINIZ SUPERMERCADOS LIMITADA | F50: 46297 | G50: 46297 | H50: 51305 | I50: 46303 | J50: 46023 | K50: 0 | L50: 46303 | M50: 0 | N50: 18638.28 | O50: Transferencia | P50: (C) BANCO BRADESCO AG. 2960-2 C/ 116071-0 | Q50: REF RECEB - CR: 4598 - NF: 51305 - PN: DINIZ SUPERMERCADOS LIMITADA | R50: Recebido | S50: =IF(C50="","",_xlfn.IFNA(_xlfn.XLOOKUP(C50,'CADASTRO CLIENTE'!$B$2:$B$9815,'CADASTRO CLIENTE'!$C$2:$C$9815),"NÃO ENCONTRADO")) -> DINIZ BOM JARDIM
A51: NS | B51: KROMA COMERCIALIZADORA DE ENERGIA LTDA | C51: C02778 | D51: IPADE - INSTITUTO PARA O DESENVOLVIMENTO DA EDUCACAO LTDA. | F51: 46241 | G51: 46241 | H51: 50070 | I51: 46244 | J51: 46023 | K51: 0 | L51: 46245 | M51: 0 | N51: 2097.7 | O51: Transferencia | P51: (C) BANCO BRADESCO AG. 2960-2 C/ 116071-0 | Q51: REF RECEB - CR: 1378 - NF: 50070 - PN: IPADE - INSTITUTO PARA O DESENVOLVIMENTO DA EDUCACAO LTDA. | R51: Recebido | S51: =IF(C51="","",_xlfn.IFNA(_xlfn.XLOOKUP(C51,'CADASTRO CLIENTE'!$B$2:$B$9815,'CADASTRO CLIENTE'!$C$2:$C$9815),"NÃO ENCONTRADO")) -> UNICHRISTUS PQL 3
A52: NS | B52: KROMA COMERCIALIZADORA DE ENERGIA LTDA | C52: C01662 | D52: SELF IT ACADEMIAS HOLDING S.A. | F52: 46209 | G52: 46209 | H52: 48855 | I52: 46217 | J52: 46023 | K52: 0 | L52: 46211 | M52: 0 | N52: 7319.12 | O52: Transferencia | P52: (C) BANCO BRADESCO AG. 2960-2 C/ 116071-0 | Q52: REF RECEB - CR: 132 - NF: 48855 - PN: SELF IT ACADEMIAS HOLDING S.A. | R52: Recebido | S52: =IF(C52="","",_xlfn.IFNA(_xlfn.XLOOKUP(C52,'CADASTRO CLIENTE'!$B$2:$B$9815,'CADASTRO CLIENTE'!$C$2:$C$9815),"NÃO ENCONTRADO")) -> SELF IT - CARUARU
A53: NS | B53: KROMA COMERCIALIZADORA DE ENERGIA LTDA | C53: C01543 | D53: H.F.M COMERCIALIZACAO DE CARNES NOBRES LTDA | F53: 46267 | G53: 46267 | H53: 50413 | I53: 46285 | J53: 46023 | K53: 0 | L53: 46283 | M53: 0 | N53: 11939.79 | O53: Transferencia | P53: (C) BANCO BRADESCO AG. 2960-2 C/ 116071-0 | Q53: REF RECEB - CR: 3804 - NF: 50413 - PN: H.F.M COMERCIALIZACAO DE CARNES NOBRES LTDA | R53: Recebido | S53: =IF(C53="","",_xlfn.IFNA(_xlfn.XLOOKUP(C53,'CADASTRO CLIENTE'!$B$2:$B$9815,'CADASTRO CLIENTE'!$C$2:$C$9815),"NÃO ENCONTRADO")) -> HFM LTDA
A54: LC | B54: KROMA GESTAO E SERVICOS EM ENERGIA ELETRICA LTDA - EPP | C54: C02934 | D54: BISCOITOS E BOLACHAS SKIN LTDA | K54: 0 | L54: 46279 | M54: 0 | N54: 469.25 | O54: Transferencia | P54: DESPESA PERDA DEVEDORES DUVIDOSOS (PDD) | Q54: REF RECEB - CR: 3233 - LC: 11851 - PN: BISCOITOS E BOLACHAS SKIN LTDA | R54: Recebido | S54: =IF(C54="","",_xlfn.IFNA(_xlfn.XLOOKUP(C54,'CADASTRO CLIENTE'!$B$2:$B$9815,'CADASTRO CLIENTE'!$C$2:$C$9815),"NÃO ENCONTRADO")) -> BISCOITOS E BOLACHAS SKIN
A55: LC | B55: KROMA GESTAO E SERVICOS EM ENERGIA ELETRICA LTDA - EPP | C55: C01358 | D55: PRIME SEAFOOD LTDA | K55: 0 | L55: 46204 | M55: 0 | N55: 3002.79 | O55: Transferencia | P55: (C) BANCO BRADESCO AG. 2960-2 C/ 225-9 | Q55: REF RECEB - CR: 2214 - LC: 12209 - PN: PRIME SEAFOOD LTDA | R55: Recebido | S55: =IF(C55="","",_xlfn.IFNA(_xlfn.XLOOKUP(C55,'CADASTRO CLIENTE'!$B$2:$B$9815,'CADASTRO CLIENTE'!$C$2:$C$9815),"NÃO ENCONTRADO")) -> PRIME SEAFOOD - BA
A56: NS | B56: KROMA COMERCIALIZADORA DE ENERGIA LTDA | C56: C02677 | D56: QUALLICAL INDUSTRIA E COMERCIO LTDA. | F56: 46206 | G56: 46206 | H56: 48573 | I56: 46213 | J56: 46023 | K56: 0 | L56: 46216 | M56: 0 | N56: 24954.31 | O56: Transferencia | P56: (C) BANCO BRADESCO AG. 2960-2 C/ 116071-0 | Q56: REF RECEB - CR: 403 - NF: 48573 - PN: QUALLICAL INDUSTRIA E COMERCIO LTDA. | R56: Recebido | S56: =IF(C56="","",_xlfn.IFNA(_xlfn.XLOOKUP(C56,'CADASTRO CLIENTE'!$B$2:$B$9815,'CADASTRO CLIENTE'!$C$2:$C$9815),"NÃO ENCONTRADO")) -> QUALLICAL INDUSTRIA
A57: NS | B57: KROMA COMERCIALIZADORA DE ENERGIA LTDA | C57: C01403 | D57: COMERCIAL DE ALIMENTOS SAN FRANCISCO LTDA | F57: 46266 | G57: 46266 | H57: 50251 | I57: 46274 | J57: 46023 | K57: 0 | L57: 46274 | M57: 0 | N57: 15464.23 | O57: Transferencia | P57: (C) BANCO BRADESCO AG. 2960-2 C/ 116071-0 | Q57: REF RECEB - CR: 3006 - NF: 50251 - PN: COMERCIAL DE ALIMENTOS SAN FRANCISCO LTDA | R57: Recebido | S57: =IF(C57="","",_xlfn.IFNA(_xlfn.XLOOKUP(C57,'CADASTRO CLIENTE'!$B$2:$B$9815,'CADASTRO CLIENTE'!$C$2:$C$9815),"NÃO ENCONTRADO")) -> SAN FRANCISCO - CAUCAIA
A58: NS | B58: KROMA COMERCIALIZADORA DE ENERGIA LTDA | C58: C02704 | D58: SOCIEDADE EDUCACIONAL JABAQUARA LTDA. | F58: 46209 | G58: 46209 | H58: 48935 | I58: 46218 | J58: 46023 | K58: 0 | L58: 46218 | M58: 0 | N58: 1085.63 | O58: Transferencia | P58: (C) BANCO BRADESCO AG. 2960-2 C/ 116071-0 | Q58: REF RECEB - CR: 621 - NF: 48935 - PN: SOCIEDADE EDUCACIONAL JABAQUARA LTDA. | R58: Recebido | S58: =IF(C58="","",_xlfn.IFNA(_xlfn.XLOOKUP(C58,'CADASTRO CLIENTE'!$B$2:$B$9815,'CADASTRO CLIENTE'!$C$2:$C$9815),"NÃO ENCONTRADO")) -> INSPIRA - MTE0004324
A59: NS | B59: KROMA COMERCIALIZADORA DE ENERGIA LTDA | C59: C00875 | D59: JB COMERCIALIZADORA DE ENERGIA LTDA | F59: 46237 | G59: 46237 | H59: 49417 | I59: 46244 | J59: 46023 | K59: 0 | L59: 46244 | M59: 0 | N59: 81908 | O59: Transferencia | P59: (C) BANCO BRADESCO AG. 2960-2 C/ 116071-0 | Q59: REF RECEB - CR: 1134 - NF: 49417 - PN: JB COMERCIALIZADORA DE ENERGIA LTDA | R59: Recebido | S59: =IF(C59="","",_xlfn.IFNA(_xlfn.XLOOKUP(C59,'CADASTRO CLIENTE'!$B$2:$B$9815,'CADASTRO CLIENTE'!$C$2:$C$9815),"NÃO ENCONTRADO")) -> JB ENERGIA
A60: LC | B60: KROMA COMERCIALIZADORA DE ENERGIA LTDA | C60: C02293 | D60: ULTRACARGO LOGISTICA S.A. | K60: 0 | L60: 46234 | M60: 0 | N60: 19179 | O60: Transferencia | P60: (T) BANCO BRADESCO AG. 2960-2 C/ 116071-0 | Q60: REF RECEB - CR: 1029 - LC: 2972 - PN: ULTRACARGO LOGISTICA S.A. | R60: Recebido | S60: =IF(C60="","",_xlfn.IFNA(_xlfn.XLOOKUP(C60,'CADASTRO CLIENTE'!$B$2:$B$9815,'CADASTRO CLIENTE'!$C$2:$C$9815),"NÃO ENCONTRADO")) -> ULTRACARGO - ITAQUI
A61: LC | B61: KROMA GESTAO E SERVICOS EM ENERGIA ELETRICA LTDA - EPP | C61: C01758 | D61: ASSOCIACAO DAS DAMAS HOSPITALEIRAS | K61: 0 | L61: 46204 | M61: 0 | N61: 938.5 | O61: Transferencia | P61: (C) BANCO BRADESCO AG. 2960-2 C/ 225-9 | Q61: REF RECEB - CR: 2056 - LC: 12324 - PN: ASSOCIACAO DAS DAMAS HOSPITALEIRAS | R61: Recebido | S61: =IF(C61="","",_xlfn.IFNA(_xlfn.XLOOKUP(C61,'CADASTRO CLIENTE'!$B$2:$B$9815,'CADASTRO CLIENTE'!$C$2:$C$9815),"NÃO ENCONTRADO")) -> COLEGIO N SRA DE LOURDES
A62: NS | B62: KROMA COMERCIALIZADORA DE ENERGIA LTDA | C62: C03121 | D62: MOINHO PRIMOR S A | F62: 46238 | G62: 46238 | H62: 49539 | I62: 46245 | J62: 46023 | K62: 0 | L62: 46245 | M62: 0 | N62: 36072.96 | O62: Transferencia | P62: (C) BANCO BRADESCO AG. 2960-2 C/ 116071-0 | Q62: REF RECEB - CR: 1368 - NF: 49539 - PN: MOINHO PRIMOR S A | R62: Recebido | S62: =IF(C62="","",_xlfn.IFNA(_xlfn.XLOOKUP(C62,'CADASTRO CLIENTE'!$B$2:$B$9815,'CADASTRO CLIENTE'!$C$2:$C$9815),"NÃO ENCONTRADO")) -> MOINHO TRABIJU
A63: NS | B63: SAO PEDRO E PAULO I SPE SA | C63: C01607 | D63: EQUATORIAL PARA DISTRIBUIDORA DE ENERGIA S.A. | F63: 46217 | G63: 46217 | H63: 1455 | I63: 46217 | J63: 46023 | K63: 0 | L63: 46223 | M63: 0 | N63: 24951.03 | O63: Transferencia | P63: (C) BANCO BRADESCO AG. 2960 C/C 219-4 | Q63: REF RECEB - CR: 890 - NF: 1455 - PN: EQUATORIAL PARA DISTRIBUIDORA DE ENERGIA S.A. | R63: Recebido | S63: =IF(C63="","",_xlfn.IFNA(_xlfn.XLOOKUP(C63,'CADASTRO CLIENTE'!$B$2:$B$9815,'CADASTRO CLIENTE'!$C$2:$C$9815),"NÃO ENCONTRADO")) -> CELPA
A64: NS | B64: KROMA COMERCIALIZADORA DE ENERGIA LTDA | C64: C01766 | D64: MASTERBOI LTDA. | F64: 46304 | G64: 46304 | H64: 51919 | I64: 46309 | J64: 46023 | K64: 0 | L64: 46309 | M64: 0 | N64: 337.37 | O64: Transferencia | P64: (C) BANCO BRADESCO AG. 2960-2 C/ 116071-0 | Q64: REF RECEB - CR: 4929 - NF: 51919 - PN: MASTERBOI LTDA. | R64: Recebido | S64: =IF(C64="","",_xlfn.IFNA(_xlfn.XLOOKUP(C64,'CADASTRO CLIENTE'!$B$2:$B$9815,'CADASTRO CLIENTE'!$C$2:$C$9815),"NÃO ENCONTRADO")) -> MASTERBOI PE
A65: NS | B65: KROMA COMERCIALIZADORA DE ENERGIA LTDA | C65: C03410 | D65: SERVICO SOCIAL DA INDUSTRIA | F65: 46206 | G65: 46206 | H65: 48645 | I65: 46211 | J65: 46023 | K65: 0 | L65: 46211 | M65: 0 | N65: 5424.7 | O65: Transferencia | P65: (C) BANCO BRADESCO AG. 2960-2 C/ 116071-0 | Q65: REF RECEB - CR: 17 - NF: 48645 - PN: SERVICO SOCIAL DA INDUSTRIA | R65: Recebido | S65: =IF(C65="","",_xlfn.IFNA(_xlfn.XLOOKUP(C65,'CADASTRO CLIENTE'!$B$2:$B$9815,'CADASTRO CLIENTE'!$C$2:$C$9815),"NÃO ENCONTRADO")) -> SESI SAUDE
A66: NS | B66: KROMA COMERCIALIZADORA DE ENERGIA LTDA | C66: C02453 | D66: NOVO ATACADO COMERCIO DE ALIMENTOS SA | F66: 46210 | G66: 46210 | H66: 49111 | I66: 46211 | J66: 46023 | K66: 0 | L66: 46211 | M66: 0 | N66: 4114.72 | O66: Transferencia | P66: (C) BANCO BRADESCO AG. 2960-2 C/ 116071-0 | Q66: REF RECEB - CR: 121 - NF: 49111 - PN: NOVO ATACADO COMERCIO DE ALIMENTOS SA | R66: Recebido | S66: =IF(C66="","",_xlfn.IFNA(_xlfn.XLOOKUP(C66,'CADASTRO CLIENTE'!$B$2:$B$9815,'CADASTRO CLIENTE'!$C$2:$C$9815),"NÃO ENCONTRADO")) -> NOVO ATACAREJO COM
A67: LC | B67: KROMA COMERCIALIZADORA DE ENERGIA LTDA | C67: C02416 | D67: FALCON HOTEIS LTDA | K67: 0 | L67: 46234 | M67: 0 | N67: 773.97 | O67: Transferencia | P67: (T) BANCO BRADESCO AG. 2960-2 C/ 116071-0 | Q67: REF RECEB - CR: 982 - LC: 2972 - PN: FALCON HOTEIS LTDA | R67: Recebido | S67: =IF(C67="","",_xlfn.IFNA(_xlfn.XLOOKUP(C67,'CADASTRO CLIENTE'!$B$2:$B$9815,'CADASTRO CLIENTE'!$C$2:$C$9815),"NÃO ENCONTRADO")) -> FALCON HOTEIS JABOATAO
A68: NS | B68: KROMA COMERCIALIZADORA DE ENERGIA LTDA | C68: C00982 | D68: GENIAL ENERGY COMERCIALIZADORA DE ENERGIA ELETRICA LTDA. | F68: 46296 | G68: 46296 | H68: 51148 | I68: 46303 | J68: 46023 | K68: 0 | L68: 46303 | M68: 0 | N68: 209160 | O68: Transferencia | P68: (C) BANCO BRADESCO AG. 2960-2 C/ 116071-0 | Q68: REF RECEB - CR: 4593 - NF: 51148 - PN: GENIAL ENERGY COMERCIALIZADORA DE ENERGIA ELETRICA LTDA. | R68: Recebido | S68: =IF(C68="","",_xlfn.IFNA(_xlfn.XLOOKUP(C68,'CADASTRO CLIENTE'!$B$2:$B$9815,'CADASTRO CLIENTE'!$C$2:$C$9815),"NÃO ENCONTRADO")) -> GENIAL ENERGY
A69: NS | B69: KROMA COMERCIALIZADORA DE ENERGIA LTDA | C69: C02254 | D69: COMERCIAL DE ALIMENTOS SAN GERARDO LTDA | F69: 46267 | G69: 46267 | H69: 50429 | I69: 46274 | J69: 46023 | K69: 0 | L69: 46274 | M69: 0 | N69: 12865.95 | O69: Transferencia | P69: (C) BANCO BRADESCO AG. 2960-2 C/ 116071-0 | Q69: REF RECEB - CR: 3014 - NF: 50429 - PN: COMERCIAL DE ALIMENTOS SAN GERARDO LTDA | R69: Recebido | S69: =IF(C69="","",_xlfn.IFNA(_xlfn.XLOOKUP(C69,'CADASTRO CLIENTE'!$B$2:$B$9815,'CADASTRO CLIENTE'!$C$2:$C$9815),"NÃO ENCONTRADO")) -> SAN GERARDO - PINDORETAMA
A70: NS | B70: FILIAL - SP - KROMA COMERCIALIZADORA DE ENERGIA LTDA | C70: C03145 | D70: AUTARQUIA MUNICIPAL DE SANEAMENTO AMBIENTAL | F70: 46240 | G70: 46240 | H70: 110 | I70: 46246 | J70: 46023 | K70: 0 | L70: 46253 | M70: 0 | N70: 34257.22 | O70: Transferencia | P70: (C) BANCO BRADESCO AG. 2960-2 C/ 116071-0 | Q70: REF RECEB - CR: 1925 - NF: 110 - PN: AUTARQUIA MUNICIPAL DE SANEAMENTO AMBIENTAL | R70: Recebido | S70: =IF(C70="","",_xlfn.IFNA(_xlfn.XLOOKUP(C70,'CADASTRO CLIENTE'!$B$2:$B$9815,'CADASTRO CLIENTE'!$C$2:$C$9815),"NÃO ENCONTRADO")) -> DAEP
A71: NS | B71: KROMA COMERCIALIZADORA DE ENERGIA LTDA | C71: C02540 | D71: SELF IT ACADEMIAS HOLDING S.A. | F71: 46239 | G71: 46239 | H71: 49802 | I71: 46248 | J71: 46023 | K71: 0 | L71: 46244 | M71: 0 | N71: 8889.26 | O71: Transferencia | P71: (C) BANCO BRADESCO AG. 2960-2 C/ 116071-0 | Q71: REF RECEB - CR: 1222 - NF: 49802 - PN: SELF IT ACADEMIAS HOLDING S.A. | R71: Recebido | S71: =IF(C71="","",_xlfn.IFNA(_xlfn.XLOOKUP(C71,'CADASTRO CLIENTE'!$B$2:$B$9815,'CADASTRO CLIENTE'!$C$2:$C$9815),"NÃO ENCONTRADO")) -> SELFIT BARÃO DE GURGUÉIA - (PI)
A72: NS | B72: KROMA COMERCIALIZADORA DE ENERGIA LTDA | C72: C03429 | D72: CIL - COMERCIO DE INFORMATICA LTDA | F72: 46211 | G72: 46211 | H72: 49162 | I72: 46216 | J72: 46023 | K72: 0 | L72: 46216 | M72: 0 | N72: 2300.4 | O72: Transferencia | P72: (C) BANCO BRADESCO AG. 2960-2 C/ 116071-0 | Q72: REF RECEB - CR: 389 - NF: 49162 - PN: CIL - COMERCIO DE INFORMATICA LTDA | R72: Recebido | S72: =IF(C72="","",_xlfn.IFNA(_xlfn.XLOOKUP(C72,'CADASTRO CLIENTE'!$B$2:$B$9815,'CADASTRO CLIENTE'!$C$2:$C$9815),"NÃO ENCONTRADO")) -> NAGEM
A73: NS | B73: KROMA COMERCIALIZADORA DE ENERGIA LTDA | C73: C03404 | D73: SERVICO SOCIAL DA INDUSTRIA | F73: 46206 | G73: 46206 | H73: 48644 | I73: 46211 | J73: 46023 | K73: 0 | L73: 46211 | M73: 0 | N73: 11029.6 | O73: Transferencia | P73: (C) BANCO BRADESCO AG. 2960-2 C/ 116071-0 | Q73: REF RECEB - CR: 13 - NF: 48644 - PN: SERVICO SOCIAL DA INDUSTRIA | R73: Recebido | S73: =IF(C73="","",_xlfn.IFNA(_xlfn.XLOOKUP(C73,'CADASTRO CLIENTE'!$B$2:$B$9815,'CADASTRO CLIENTE'!$C$2:$C$9815),"NÃO ENCONTRADO")) -> SESI PAULISTA
A74: NS | B74: KROMA COMERCIALIZADORA DE ENERGIA LTDA | C74: C01494 | D74: DUCOCO PRODUTOS ALIMENTICIOS S/A | F74: 46209 | G74: 46209 | H74: 48840 | I74: 46213 | J74: 46023 | K74: 0 | L74: 46213 | M74: 0 | N74: 1010227.8 | O74: Transferencia | P74: (C) BANCO BNB AG. 44 C/ 49680-0 | Q74: REF RECEB - CR: 197 - NF: 48840 - PN: DUCOCO PRODUTOS ALIMENTICIOS S/A | R74: Recebido | S74: =IF(C74="","",_xlfn.IFNA(_xlfn.XLOOKUP(C74,'CADASTRO CLIENTE'!$B$2:$B$9815,'CADASTRO CLIENTE'!$C$2:$C$9815),"NÃO ENCONTRADO")) -> DUCOCO
A75: LC | B75: KROMA GESTAO E SERVICOS EM ENERGIA ELETRICA LTDA - EPP | C75: C01724 | D75: CONDOMINIO DO EDIFICIO EMPRESARIAL GRAHAM BELL | K75: 0 | L75: 46204 | M75: 0 | N75: 645.47 | O75: Transferencia | P75: (C) BANCO BRADESCO AG. 2960-2 C/ 225-9 | Q75: REF RECEB - CR: 2092 - LC: 12378 - PN: CONDOMINIO DO EDIFICIO EMPRESARIAL GRAHAM BELL | R75: Recebido | S75: =IF(C75="","",_xlfn.IFNA(_xlfn.XLOOKUP(C75,'CADASTRO CLIENTE'!$B$2:$B$9815,'CADASTRO CLIENTE'!$C$2:$C$9815),"NÃO ENCONTRADO")) -> EMPRESARIAL GRAHAM BELL
A76: NS | B76: KROMA COMERCIALIZADORA DE ENERGIA LTDA | C76: C00701 | D76: SUPERMERCADO COMETA LTDA | F76: 46276 | G76: 46276 | H76: 51010 | I76: 46276 | J76: 46023 | K76: 0 | L76: 46283 | M76: 0 | N76: 56227.8 | O76: Transferencia | P76: (C) BANCO BRADESCO AG. 2960-2 C/ 116071-0 | Q76: REF RECEB - CR: 3820 - NF: 51010 - PN: SUPERMERCADO COMETA LTDA | R76: Recebido | S76: =IF(C76="","",_xlfn.IFNA(_xlfn.XLOOKUP(C76,'CADASTRO CLIENTE'!$B$2:$B$9815,'CADASTRO CLIENTE'!$C$2:$C$9815),"NÃO ENCONTRADO")) -> SUPERM. COMETA I.A.
A77: NS | B77: KROMA COMERCIALIZADORA DE ENERGIA LTDA | C77: C01512 | D77: COMERCIAL DE ALIMENTOS SAN FRANCISCO LTDA | F77: 46205 | G77: 46205 | H77: 48335 | I77: 46211 | J77: 46023 | K77: 0 | L77: 46211 | M77: 0 | N77: 16173.46 | O77: Transferencia | P77: (C) BANCO BRADESCO AG. 2960-2 C/ 116071-0 | Q77: REF RECEB - CR: 146 - NF: 48335 - PN: COMERCIAL DE ALIMENTOS SAN FRANCISCO LTDA | R77: Recebido | S77: =IF(C77="","",_xlfn.IFNA(_xlfn.XLOOKUP(C77,'CADASTRO CLIENTE'!$B$2:$B$9815,'CADASTRO CLIENTE'!$C$2:$C$9815),"NÃO ENCONTRADO")) -> SUP. SAN FRANCISCO
A78: NS | B78: KROMA COMERCIALIZADORA DE ENERGIA LTDA | C78: C02340 | D78: INSPIRA MUDANCA PARTICIPACOES S/A | F78: 46301 | G78: 46301 | H78: 51646 | I78: 46310 | J78: 46023 | K78: 0 | L78: 46309 | M78: 0 | N78: 39221.7 | O78: Transferencia | P78: (C) BANCO BRADESCO AG. 2960-2 C/ 116071-0 | Q78: REF RECEB - CR: 4938 - NF: 51646 - PN: INSPIRA MUDANCA PARTICIPACOES S/A | R78: Recebido | S78: =IF(C78="","",_xlfn.IFNA(_xlfn.XLOOKUP(C78,'CADASTRO CLIENTE'!$B$2:$B$9815,'CADASTRO CLIENTE'!$C$2:$C$9815),"NÃO ENCONTRADO")) -> INSPIRA MUDANÇA - UNID 26
A79: NS | B79: KROMA COMERCIALIZADORA DE ENERGIA LTDA | C79: C03068 | D79: SER EDUCACIONAL S.A. | F79: 46260 | G79: 46260 | H79: 2026082604 | I79: 46267 | J79: 46023 | K79: 0 | L79: 46267 | M79: 0 | N79: 278.73 | O79: Transferencia | P79: (C) BANCO BRADESCO AG. 2960-2 C/ 116071-0 | Q79: REF RECEB - CR: 2843 - NF: 2026082604 - PN: SER EDUCACIONAL S.A. | R79: Recebido | S79: =IF(C79="","",_xlfn.IFNA(_xlfn.XLOOKUP(C79,'CADASTRO CLIENTE'!$B$2:$B$9815,'CADASTRO CLIENTE'!$C$2:$C$9815),"NÃO ENCONTRADO")) -> SER EDUCACIONAL S.A. NATAL
A80: NS | B80: KROMA COMERCIALIZADORA DE ENERGIA LTDA | C80: C03429 | D80: CIL - COMERCIO DE INFORMATICA LTDA | F80: 46269 | G80: 46269 | H80: 50764 | I80: 46276 | J80: 46023 | K80: 0 | L80: 46276 | M80: 0 | N80: 6027.48 | O80: Transferencia | P80: (C) BANCO BRADESCO AG. 2960-2 C/ 116071-0 | Q80: REF RECEB - CR: 3256 - NF: 50764 - PN: CIL - COMERCIO DE INFORMATICA LTDA | R80: Recebido | S80: =IF(C80="","",_xlfn.IFNA(_xlfn.XLOOKUP(C80,'CADASTRO CLIENTE'!$B$2:$B$9815,'CADASTRO CLIENTE'!$C$2:$C$9815),"NÃO ENCONTRADO")) -> NAGEM
A81: NS | B81: KROMA COMERCIALIZADORA DE ENERGIA LTDA | C81: C02924 | D81: KROMA COMERCIALIZADORA DE ENERGIA LTDA | F81: 46212 | G81: 46212 | H81: 49174 | I81: 46223 | J81: 46023 | K81: 0 | L81: 46234 | M81: 0 | N81: 457832.59 | O81: Transferencia | P81: (T) BANCO BRADESCO AG. 2960-2 C/ 116071-0 | Q81: REF RECEB - CR: 944 - NF: 49174 - PN: KROMA COMERCIALIZADORA DE ENERGIA LTDA | R81: Recebido | S81: =IF(C81="","",_xlfn.IFNA(_xlfn.XLOOKUP(C81,'CADASTRO CLIENTE'!$B$2:$B$9815,'CADASTRO CLIENTE'!$C$2:$C$9815),"NÃO ENCONTRADO")) -> KROMA PB
A82: NS | B82: KROMA COMERCIALIZADORA DE ENERGIA LTDA | C82: C00878 | D82: VENOSAN BRASIL LTDA | F82: 46300 | G82: 46300 | H82: 51486 | I82: 46303 | J82: 46023 | K82: 0 | L82: 46303 | M82: 0 | N82: 33911.44 | O82: Transferencia | P82: (C) BANCO BRADESCO AG. 2960-2 C/ 116071-0 | Q82: REF RECEB - CR: 4557 - NF: 51486 - PN: VENOSAN BRASIL LTDA | R82: Recebido | S82: =IF(C82="","",_xlfn.IFNA(_xlfn.XLOOKUP(C82,'CADASTRO CLIENTE'!$B$2:$B$9815,'CADASTRO CLIENTE'!$C$2:$C$9815),"NÃO ENCONTRADO")) -> VENOSAN BRASIL
A83: NS | B83: KROMA COMERCIALIZADORA DE ENERGIA LTDA | C83: C01668 | D83: BONANZA SUPERMERCADOS LTDA EM RECUPERACAO JUDICIAL | F83: 46302 | G83: 46302 | H83: 51874 | I83: 46307 | J83: 46023 | K83: 0 | L83: 46308 | M83: 0 | N83: 19305.66 | O83: Transferencia | P83: (C) BANCO BNB AG. 44 C/ 49680-0 | Q83: REF RECEB - CR: 4889 - NF: 51874 - PN: BONANZA SUPERMERCADOS LTDA EM RECUPERACAO JUDICIAL | R83: Recebido | S83: =IF(C83="","",_xlfn.IFNA(_xlfn.XLOOKUP(C83,'CADASTRO CLIENTE'!$B$2:$B$9815,'CADASTRO CLIENTE'!$C$2:$C$9815),"NÃO ENCONTRADO")) -> SUPERM. BONANZA 9
A84: NS | B84: FILIAL - CE - KROMA COMERCIALIZADORA DE ENERGIA LTDA | C84: C00718 | D84: INDUSTRIA E COMERCIO DE GELO PRIMOR LTDA | F84: 46301 | G84: 46301 | H84: 1144 | I84: 46303 | J84: 46023 | K84: 0 | L84: 46302 | M84: 0 | N84: 96925.53 | O84: Transferencia | P84: (C) BANCO BRADESCO AG. 2960-2 C/ 116071-0 | Q84: REF RECEB - CR: 4653 - NF: 1144 - PN: INDUSTRIA E COMERCIO DE GELO PRIMOR LTDA | R84: Recebido | S84: =IF(C84="","",_xlfn.IFNA(_xlfn.XLOOKUP(C84,'CADASTRO CLIENTE'!$B$2:$B$9815,'CADASTRO CLIENTE'!$C$2:$C$9815),"NÃO ENCONTRADO")) -> GELO PRIMOR
A85: NS | B85: FILIAL - SP - KROMA COMERCIALIZADORA DE ENERGIA LTDA | C85: C03145 | D85: AUTARQUIA MUNICIPAL DE SANEAMENTO AMBIENTAL | F85: 46240 | G85: 46240 | H85: 112 | I85: 46246 | J85: 46023 | K85: 0 | L85: 46253 | M85: 0 | N85: 4228.97 | O85: Transferencia | P85: (C) BANCO BRADESCO AG. 2960-2 C/ 116071-0 | Q85: REF RECEB - CR: 1927 - NF: 112 - PN: AUTARQUIA MUNICIPAL DE SANEAMENTO AMBIENTAL | R85: Recebido | S85: =IF(C85="","",_xlfn.IFNA(_xlfn.XLOOKUP(C85,'CADASTRO CLIENTE'!$B$2:$B$9815,'CADASTRO CLIENTE'!$C$2:$C$9815),"NÃO ENCONTRADO")) -> DAEP
A86: NS | B86: KROMA COMERCIALIZADORA DE ENERGIA LTDA | C86: C01344 | D86: MC COMERCIO DE CARNES NOBRES LTDA | F86: 46213 | G86: 46213 | H86: 49240 | I86: 46218 | J86: 46023 | K86: 0 | L86: 46231 | M86: 113.47 | N86: 11233.04 | O86: Transferencia | P86: (C) BANCO BRADESCO AG. 2960-2 C/ 116071-0 | Q86: REF RECEB - CR: 857 - NF: 49240 - PN: MC COMERCIO DE CARNES NOBRES LTDA | R86: Recebido | S86: =IF(C86="","",_xlfn.IFNA(_xlfn.XLOOKUP(C86,'CADASTRO CLIENTE'!$B$2:$B$9815,'CADASTRO CLIENTE'!$C$2:$C$9815),"NÃO ENCONTRADO")) -> MC COMERCIO DE CARNES NOBRES
A87: LC | B87: KROMA GESTAO E SERVICOS EM ENERGIA ELETRICA LTDA - EPP | C87: C03435 | D87: ROBERTO MOURA DE ARRUDA FALCAO | K87: 0 | L87: 46204 | M87: 0 | N87: 822.61 | O87: Transferencia | P87: (C) BANCO BRADESCO AG. 2960-2 C/ 225-9 | Q87: REF RECEB - CR: 2076 - LC: 12353 - PN: ROBERTO MOURA DE ARRUDA FALCAO | R87: Recebido | S87: =IF(C87="","",_xlfn.IFNA(_xlfn.XLOOKUP(C87,'CADASTRO CLIENTE'!$B$2:$B$9815,'CADASTRO CLIENTE'!$C$2:$C$9815),"NÃO ENCONTRADO")) -> ROBERTO MOURA DE ARRUDA FALCAO
A88: LC | B88: KROMA GESTAO E SERVICOS EM ENERGIA ELETRICA LTDA - EPP | C88: C01060 | D88: COMPANHIA GERACAO DE ENERGIA PILAO | K88: 0 | L88: 46314 | M88: 0 | N88: 5409.97 | O88: Transferencia | P88: DESPESA PERDA DEVEDORES DUVIDOSOS (PDD) | Q88: REF RECEB - CR: 5199 - LC: 12193 - PN: COMPANHIA GERACAO DE ENERGIA PILAO | R88: Recebido | S88: =IF(C88="","",_xlfn.IFNA(_xlfn.XLOOKUP(C88,'CADASTRO CLIENTE'!$B$2:$B$9815,'CADASTRO CLIENTE'!$C$2:$C$9815),"NÃO ENCONTRADO")) -> UHE SALTO PILAO
A89: LC | B89: KROMA COMERCIALIZADORA DE ENERGIA LTDA | C89: C02005 | D89: SQUADRA COMERCIALIZADORA DE ENERGIA LTDA | K89: 0 | L89: 46211 | M89: 0 | N89: 253800 | O89: Transferencia | P89: (C) BANCO ASA AG. 1-9 C/ 600000530-5 | Q89: REF RECEB - CR: 281 - LC: 2972 - PN: SQUADRA COMERCIALIZADORA DE ENERGIA LTDA | R89: Recebido | S89: =IF(C89="","",_xlfn.IFNA(_xlfn.XLOOKUP(C89,'CADASTRO CLIENTE'!$B$2:$B$9815,'CADASTRO CLIENTE'!$C$2:$C$9815),"NÃO ENCONTRADO")) -> SQUADRA ENERGIA
A90: NS | B90: KROMA COMERCIALIZADORA DE ENERGIA LTDA | C90: C02770 | D90: PROJEART INDUSTRIA DE ESTRUTURAS METALICAS LTDA | F90: 46269 | G90: 46269 | H90: 50791 | I90: 46279 | J90: 46023 | K90: 0 | L90: 46279 | M90: 0 | N90: 1137.55 | O90: Transferencia | P90: (C) BANCO BRADESCO AG. 2960-2 C/ 116071-0 | Q90: REF RECEB - CR: 3415 - NF: 50791 - PN: PROJEART INDUSTRIA DE ESTRUTURAS METALICAS LTDA | R90: Recebido | S90: =IF(C90="","",_xlfn.IFNA(_xlfn.XLOOKUP(C90,'CADASTRO CLIENTE'!$B$2:$B$9815,'CADASTRO CLIENTE'!$C$2:$C$9815),"NÃO ENCONTRADO")) -> PROJEART
A91: NS | B91: KROMA COMERCIALIZADORA DE ENERGIA LTDA | C91: C02119 | D91: COMANDO DA MARINHA | F91: 46238 | G91: 46238 | H91: 49569 | I91: 46255 | J91: 46023 | K91: 0 | L91: 46254 | M91: 0 | N91: 66718.64 | O91: Transferencia | P91: (C) BANCO BRADESCO AG. 2960-2 C/ 116071-0 | Q91: REF RECEB - CR: 1868 - NF: 49569 - PN: COMANDO DA MARINHA | R91: Recebido | S91: =IF(C91="","",_xlfn.IFNA(_xlfn.XLOOKUP(C91,'CADASTRO CLIENTE'!$B$2:$B$9815,'CADASTRO CLIENTE'!$C$2:$C$9815),"NÃO ENCONTRADO")) -> BNA
A92: NS | B92: KROMA COMERCIALIZADORA DE ENERGIA LTDA | C92: C02013 | D92: ABC BRASIL COMERCIALIZADORA DE ENERGIA LTDA. | F92: 46237 | G92: 46237 | H92: 49421 | I92: 46244 | J92: 46023 | K92: 0 | L92: 46251 | M92: 0 | N92: 572880 | O92: Transferencia | P92: (T) BANCO BRADESCO AG. 2960-2 C/ 116071-0 | Q92: REF RECEB - CR: 1551 - NF: 49421 - PN: ABC BRASIL COMERCIALIZADORA DE ENERGIA LTDA. | R92: Recebido | S92: =IF(C92="","",_xlfn.IFNA(_xlfn.XLOOKUP(C92,'CADASTRO CLIENTE'!$B$2:$B$9815,'CADASTRO CLIENTE'!$C$2:$C$9815),"NÃO ENCONTRADO")) -> ABC BRASIL
A93: NS | B93: FILIAL - PB - KROMA COMERCIALIZADORA DE ENERGIA LTDA | C93: C02912 | D93: COMPANHIA DE AGUA E ESGOTOS DA PARAIBA CAGEPA | F93: 46248 | G93: 46248 | H93: 409 | I93: 46254 | J93: 46023 | K93: 0 | L93: 46254 | M93: 0 | N93: 158.86 | O93: Transferencia | P93: (C) BANCO BRADESCO AG. 2960-2 C/ 116071-0 | Q93: REF RECEB - CR: 1870 - NF: 409 - PN: COMPANHIA DE AGUA E ESGOTOS DA PARAIBA CAGEPA | R93: Recebido | S93: =IF(C93="","",_xlfn.IFNA(_xlfn.XLOOKUP(C93,'CADASTRO CLIENTE'!$B$2:$B$9815,'CADASTRO CLIENTE'!$C$2:$C$9815),"NÃO ENCONTRADO")) -> CAGEPA
A94: NS | B94: KROMA COMERCIALIZADORA DE ENERGIA LTDA | C94: C01691 | D94: CARAPITANGA INDUSTRIA DE PESCADOS DO BRASIL LTDA | F94: 46297 | G94: 46297 | H94: 51363 | I94: 46310 | J94: 46023 | K94: 0 | L94: 46309 | M94: 0 | N94: 66640.16 | O94: Transferencia | P94: (C) BANCO BRADESCO AG. 2960-2 C/ 116071-0 | Q94: REF RECEB - CR: 4935 - NF: 51363 - PN: CARAPITANGA INDUSTRIA DE PESCADOS DO BRASIL LTDA | R94: Recebido | S94: =IF(C94="","",_xlfn.IFNA(_xlfn.XLOOKUP(C94,'CADASTRO CLIENTE'!$B$2:$B$9815,'CADASTRO CLIENTE'!$C$2:$C$9815),"NÃO ENCONTRADO")) -> CARAPITANGA
A95: NS | B95: SAO PEDRO E PAULO I SPE SA | C95: C01845 | D95: AMPLA ENERGIA E SERVICOS S.A. | F95: 46217 | G95: 46217 | H95: 1469 | I95: 46217 | J95: 46023 | K95: 0 | L95: 46233 | M95: 0 | N95: 28143.2 | O95: Transferencia | P95: (C) BANCO BRADESCO AG. 2960 C/C 219-4 | Q95: REF RECEB - CR: 904 - NF: 1469 - PN: AMPLA ENERGIA E SERVICOS S.A. | R95: Recebido | S95: =IF(C95="","",_xlfn.IFNA(_xlfn.XLOOKUP(C95,'CADASTRO CLIENTE'!$B$2:$B$9815,'CADASTRO CLIENTE'!$C$2:$C$9815),"NÃO ENCONTRADO")) -> AMPLA
A96: LC | B96: KROMA GESTAO E SERVICOS EM ENERGIA ELETRICA LTDA - EPP | C96: C02351 | D96: MOBILE HOUSE ARTEFATOS DE MADEIRA LTDA | K96: 0 | L96: 46204 | M96: 0 | N96: 835.08 | O96: Transferencia | P96: (C) BANCO BRADESCO AG. 2960-2 C/ 225-9 | Q96: REF RECEB - CR: 2069 - LC: 12339 - PN: MOBILE HOUSE ARTEFATOS DE MADEIRA LTDA | R96: Recebido | S96: =IF(C96="","",_xlfn.IFNA(_xlfn.XLOOKUP(C96,'CADASTRO CLIENTE'!$B$2:$B$9815,'CADASTRO CLIENTE'!$C$2:$C$9815),"NÃO ENCONTRADO")) -> MOBILE HOUSE
A97: NS | B97: KROMA COMERCIALIZADORA DE ENERGIA LTDA | C97: C02453 | D97: NOVO ATACADO COMERCIO DE ALIMENTOS SA | F97: 46269 | G97: 46269 | H97: 50798 | I97: 46274 | J97: 46023 | K97: 0 | L97: 46274 | M97: 0 | N97: 307172.17 | O97: Transferencia | P97: (C) BANCO BRADESCO AG. 2960-2 C/ 116071-0 | Q97: REF RECEB - CR: 2998 - NF: 50798 - PN: NOVO ATACADO COMERCIO DE ALIMENTOS SA | R97: Recebido | S97: =IF(C97="","",_xlfn.IFNA(_xlfn.XLOOKUP(C97,'CADASTRO CLIENTE'!$B$2:$B$9815,'CADASTRO CLIENTE'!$C$2:$C$9815),"NÃO ENCONTRADO")) -> NOVO ATACAREJO COM
A98: NS | B98: KROMA COMERCIALIZADORA DE ENERGIA LTDA | C98: C02227 | D98: APEL ATIVIDADES PRO ENSINO LTDA | F98: 46238 | G98: 46238 | H98: 49670 | I98: 46244 | J98: 46023 | K98: 0 | L98: 46241 | M98: 0 | N98: 1871.56 | O98: Transferencia | P98: (C) BANCO BRADESCO AG. 2960-2 C/ 116071-0 | Q98: REF RECEB - CR: 1389 - NF: 49670 - PN: APEL ATIVIDADES PRO ENSINO LTDA | R98: Recebido | S98: =IF(C98="","",_xlfn.IFNA(_xlfn.XLOOKUP(C98,'CADASTRO CLIENTE'!$B$2:$B$9815,'CADASTRO CLIENTE'!$C$2:$C$9815),"NÃO ENCONTRADO")) -> COLEGIO CHRISTUS - N. VALENTE
A99: NS | B99: KROMA COMERCIALIZADORA DE ENERGIA LTDA | C99: C00040 | D99: IPADE - INSTITUTO PARA O DESENVOLVIMENTO DA EDUCACAO LTDA. | F99: 46238 | G99: 46238 | H99: 49686 | I99: 46244 | J99: 46023 | K99: 0 | L99: 46241 | M99: 0 | N99: 5338.96 | O99: Transferencia | P99: (C) BANCO BRADESCO AG. 2960-2 C/ 116071-0 | Q99: REF RECEB - CR: 1392 - NF: 49686 - PN: IPADE - INSTITUTO PARA O DESENVOLVIMENTO DA EDUCACAO LTDA. | R99: Recebido | S99: =IF(C99="","",_xlfn.IFNA(_xlfn.XLOOKUP(C99,'CADASTRO CLIENTE'!$B$2:$B$9815,'CADASTRO CLIENTE'!$C$2:$C$9815),"NÃO ENCONTRADO")) -> IPADE
A100: NS | B100: KROMA COMERCIALIZADORA DE ENERGIA LTDA | C100: C02794 | D100: NATUCOCO COMERCIO ATACADISTA DE ALIMENTOS LTDA | F100: 46238 | G100: 46238 | H100: 49485 | I100: 46244 | J100: 46023 | K100: 0 | L100: 46244 | M100: 0 | N100: 4137.46 | O100: Transferencia | P100: (C) BANCO BRADESCO AG. 2960-2 C/ 116071-0 | Q100: REF RECEB - CR: 1112 - NF: 49485 - PN: NATUCOCO COMERCIO ATACADISTA DE ALIMENTOS LTDA | R100: Recebido | S100: =IF(C100="","",_xlfn.IFNA(_xlfn.XLOOKUP(C100,'CADASTRO CLIENTE'!$B$2:$B$9815,'CADASTRO CLIENTE'!$C$2:$C$9815),"NÃO ENCONTRADO")) -> NATUCOCO
...

Sheet TITULOS ABERTO ANTIGO ATE 30.06
A1: Selection | B1: Filial | C1: Documento | D1: Tipo Documento | E1: Série do Documento | F1: Código Parceiro | G1: Nome Fantasia do Parceiro | H1: Saldo Parcela | I1: Nome Parceiro | J1: CNPJ/CPF | K1: Nº parcela | L1: Valor Parcela | M1: Valor Desconto | N1: Valor Total Juros | O1: Total Pagamento | P1: Total Atualizado | Q1: Moeda | R1: Taxa Moeda | S1: Valor Parcela ME | T1: Saldo Parcela ME | U1: Valor Imposto Retido no Pagamento | V1: Data Documento | W1: Data Vencimento | X1: Dias Atraso | Y1: Observações | Z1: Contrato | AA1: Forma de Pagamento | AB1: Nosso Número | AC1: Número de Controle | AD1: Linha Digitável | AE1: Status Boleto | AF1: Situação Boleto | AG1: Vendedor | AH1: Projeto | AI1: Modelo | AJ1: UF Cobrança | AK1: Município Cobrança | AL1: Total Atualizado ME | AM1: Número da NFS-e | AN1: Ref.1 | AO1: Informação Cobrança | AP1: Forma de Pagamento da Parcela | AQ1: Total Pagamento ME | AR1: Multa % | AS1: Valor Multa | AT1: Valor Multa ME | AU1: Juros % | AV1: Valor Total Juros ME | AW1: Desconto % | AX1: Valor Desconto ME
A2: FALSE | B2: 9 - KROMA GESTAO E SERVICOS EM ENERGIA ELETRICA | C2: 12197 | D2: Lançamento Contábil Manual | E2: 10589 | F2: C03018 | G2: ARAPUA PARTICIPACOES | H2: 26655 | I2: ARAPUA PARTICIPACOES S.A | J2: 43674701000119 | K2: 0 | L2: 26655 | M2: 0 | N2: 0 | O2: 26655 | P2: 26655 | Q2: R$ | R2: 0 | S2: 0 | T2: 0 | U2: 0 | V2: 46203 | W2: 46325 | X2: 113 | Y2: VLR REF SRV GESTAO NF 349 ARAPUA PARTICIPACOES | AE2: Não Informado | AF2: Não Informado | AL2: 0 | AQ2: 0 | AR2: 0 | AS2: 0 | AT2: 0 | AU2: 0 | AV2: 0 | AW2: 0 | AX2: 0
A3: FALSE | B3: 9 - KROMA GESTAO E SERVICOS EM ENERGIA ELETRICA | C3: 12194 | D3: Lançamento Contábil Manual | E3: 10586 | F3: C02693 | G3: TBFORTE - SP | H3: 4728 | I3: TBFORTE SEGURANCA E TRANSPORTE DE VALORES LTDA. | J3: 09262608000169 | K3: 0 | L3: 4728 | M3: 0 | N3: 0 | O3: 4728 | P3: 4728 | Q3: R$ | R3: 0 | S3: 0 | T3: 0 | U3: 0 | V3: 46203 | W3: 46203 | X3: 113 | Y3: VLR REF SRV GESTAO NF 338 TBFORTE - SP | AE3: Não Informado | AF3: Não Informado | AL3: 0 | AQ3: 0 | AR3: 0 | AS3: 0 | AT3: 0 | AU3: 0 | AV3: 0 | AW3: 0 | AX3: 0
A4: FALSE | B4: 9 - KROMA GESTAO E SERVICOS EM ENERGIA ELETRICA | C4: 11898 | D4: Lançamento Contábil Manual | E4: 10291 | F4: C00915 | G4: HOSP. JAYME DA FONTE | H4: 3147.74 | I4: ORGANIZACAO HOSPITALAR DE PERNAMBUCO LTDA | J4: 11.452.240/0001-43 | K4: 0 | L4: 3147.74 | M4: 0 | N4: 0 | O4: 3147.74 | P4: 3147.74 | Q4: R$ | R4: 0 | S4: 0 | T4: 0 | U4: 0 | V4: 46203 | W4: 46022 | X4: 294 | Y4: VLR REF SRV GESTAO NF 8024 HOSP. JAYME DA FONTE | AE4: Não Informado | AF4: Não Informado | AL4: 0 | AQ4: 0 | AR4: 0 | AS4: 0 | AT4: 0 | AU4: 0 | AV4: 0 | AW4: 0 | AX4: 0
A5: FALSE | B5: 9 - KROMA GESTAO E SERVICOS EM ENERGIA ELETRICA | C5: 12189 | D5: Lançamento Contábil Manual | E5: 10581 | F5: C01358 | G5: PRIME SEAFOOD - BA | H5: 3002.79 | I5: PRIME SEAFOOD LTDA | J5: 15452593000366 | K5: 0 | L5: 3002.79 | M5: 0 | N5: 0 | O5: 3002.79 | P5: 3002.79 | Q5: R$ | R5: 0 | S5: 0 | T5: 0 | U5: 0 | V5: 46203 | W5: 46188 | X5: 128 | Y5: VLR REF SRV GESTAO NF 40 PRIME SEAFOOD - BA | AE5: Não Informado | AF5: Não Informado | AL5: 0 | AQ5: 0 | AR5: 0 | AS5: 0 | AT5: 0 | AU5: 0 | AV5: 0 | AW5: 0 | AX5: 0
A6: FALSE | B6: 9 - KROMA GESTAO E SERVICOS EM ENERGIA ELETRICA | C6: 12190 | D6: Lançamento Contábil Manual | E6: 10582 | F6: C02893 | G6: PRIME SEAFOOD - PA | H6: 3002.79 | I6: PRIME SEAFOOD LTDA | J6: 15452593001176 | K6: 0 | L6: 3002.79 | M6: 0 | N6: 0 | O6: 3002.79 | P6: 3002.79 | Q6: R$ | R6: 0 | S6: 0 | T6: 0 | U6: 0 | V6: 46203 | W6: 46188 | X6: 128 | Y6: VLR REF SRV GESTAO NF 90 PRIME SEAFOOD - PA | AE6: Não Informado | AF6: Não Informado | AL6: 0 | AQ6: 0 | AR6: 0 | AS6: 0 | AT6: 0 | AU6: 0 | AV6: 0 | AW6: 0 | AX6: 0
A7: FALSE | B7: 9 - KROMA GESTAO E SERVICOS EM ENERGIA ELETRICA | C7: 11950 | D7: Lançamento Contábil Manual | E7: 10343 | F7: C02188 | G7: MESSEJANA | H7: 2960.97 | I7: MESSEJANA CENTER EMPREENDIMENTOS LTDA | J7: 35364021000170 | K7: 0 | L7: 2960.97 | M7: 0 | N7: 0 | O7: 2960.97 | P7: 2960.97 | Q7: R$ | R7: 0 | S7: 0 | T7: 0 | U7: 0 | V7: 46203 | W7: 46052 | X7: 264 | Y7: VLR REF SRV GESTAO NF 231 MESSEJANA | AE7: Não Informado | AF7: Não Informado | AL7: 0 | AQ7: 0 | AR7: 0 | AS7: 0 | AT7: 0 | AU7: 0 | AV7: 0 | AW7: 0 | AX7: 0
A8: FALSE | B8: 9 - KROMA GESTAO E SERVICOS EM ENERGIA ELETRICA | C8: 12121 | D8: Lançamento Contábil Manual | E8: 10513 | F8: C00871 | G8: CAMPIMAGEM | H8: 2665.26 | I8: CAMPIMAGEM-CENTRO DE DIAG.POR IMAGEM DE CAMP.GRANDE LTDA | J8: 02503493000108 | K8: 0 | L8: 2665.26 | M8: 0 | N8: 0 | O8: 2665.26 | P8: 2665.26 | Q8: R$ | R8: 0 | S8: 0 | T8: 0 | U8: 0 | V8: 46203 | W8: 46142 | X8: 174 | Y8: VLR REF SRV GESTAO NF 1361 CAMPIMAGEM | AE8: Não Informado | AF8: Não Informado | AL8: 0 | AQ8: 0 | AR8: 0 | AS8: 0 | AT8: 0 | AU8: 0 | AV8: 0 | AW8: 0 | AX8: 0
A9: FALSE | B9: 9 - KROMA GESTAO E SERVICOS EM ENERGIA ELETRICA | C9: 12226 | D9: Lançamento Contábil Manual | E9: 10618 | F9: C02103 | G9: ATACADAO DM LTDA | H9: 2579.9 | I9: ATACADAO DM LTDA | J9: 03369825000176 | K9: 0 | L9: 2579.9 | M9: 0 | N9: 0 | O9: 2579.9 | P9: 2579.9 | Q9: R$ | R9: 0 | S9: 0 | T9: 0 | U9: 0 | V9: 46203 | W9: 46203 | X9: 113 | Y9: VLR REF SRV GESTAO NF 385 ATACADAO DM LTDA | AE9: Não Informado | AF9: Não Informado | AL9: 0 | AQ9: 0 | AR9: 0 | AS9: 0 | AT9: 0 | AU9: 0 | AV9: 0 | AW9: 0 | AX9: 0
A10: FALSE | B10: 9 - KROMA GESTAO E SERVICOS EM ENERGIA ELETRICA | C10: 11941 | D10: Lançamento Contábil Manual | E10: 10334 | F10: C02393 | G10: SPP V | H10: 2462.5 | I10: SAO PEDRO E PAULO V ENERGIA SPE S/A | J10: 30997905000149 | K10: 0 | L10: 2462.5 | M10: 0 | N10: 0 | O10: 2462.5 | P10: 2462.5 | Q10: R$ | R10: 0 | S10: 0 | T10: 0 | U10: 0 | V10: 46203 | W10: 46325 | X10: 264 | Y10: VLR REF SRV GESTAO NF 253 SPP V | AE10: Não Informado | AF10: Não Informado | AL10: 0 | AQ10: 0 | AR10: 0 | AS10: 0 | AT10: 0 | AU10: 0 | AV10: 0 | AW10: 0 | AX10: 0
A11: FALSE | B11: 9 - KROMA GESTAO E SERVICOS EM ENERGIA ELETRICA | C11: 12138 | D11: Lançamento Contábil Manual | E11: 10530 | F11: C02393 | G11: SPP V | H11: 2462.5 | I11: SAO PEDRO E PAULO V ENERGIA SPE S/A | J11: 30997905000149 | K11: 0 | L11: 2462.5 | M11: 0 | N11: 0 | O11: 2462.5 | P11: 2462.5 | Q11: R$ | R11: 0 | S11: 0 | T11: 0 | U11: 0 | V11: 46203 | W11: 46325 | X11: 128 | Y11: VLR REF SRV GESTAO NF 62 SPP V | AE11: Não Informado | AF11: Não Informado | AL11: 0 | AQ11: 0 | AR11: 0 | AS11: 0 | AT11: 0 | AU11: 0 | AV11: 0 | AW11: 0 | AX11: 0
A12: FALSE | B12: 9 - KROMA GESTAO E SERVICOS EM ENERGIA ELETRICA | C12: 11881 | D12: Lançamento Contábil Manual | E12: 10274 | F12: C01840 | G12: MR PHARMA | H12: 2373.52 | I12: MR PHARMA S.A | J12: 23668196000192 | K12: 0 | L12: 2373.52 | M12: 0 | N12: 0 | O12: 2373.52 | P12: 2373.52 | Q12: R$ | R12: 0 | S12: 0 | T12: 0 | U12: 0 | V12: 46203 | W12: 46022 | X12: 294 | Y12: VLR REF SRV GESTAO NF 7785 MR PHARMA | AE12: Não Informado | AF12: Não Informado | AL12: 0 | AQ12: 0 | AR12: 0 | AS12: 0 | AT12: 0 | AU12: 0 | AV12: 0 | AW12: 0 | AX12: 0
A13: FALSE | B13: 9 - KROMA GESTAO E SERVICOS EM ENERGIA ELETRICA | C13: 12013 | D13: Lançamento Contábil Manual | E13: 10406 | F13: C01840 | G13: MR PHARMA | H13: 2373.52 | I13: MR PHARMA S.A | J13: 23668196000192 | K13: 0 | L13: 2373.52 | M13: 0 | N13: 0 | O13: 2373.52 | P13: 2373.52 | Q13: R$ | R13: 0 | S13: 0 | T13: 0 | U13: 0 | V13: 46203 | W13: 46112 | X13: 204 | Y13: VLR REF SRV GESTAO NF 772 MR PHARMA | AE13: Não Informado | AF13: Não Informado | AL13: 0 | AQ13: 0 | AR13: 0 | AS13: 0 | AT13: 0 | AU13: 0 | AV13: 0 | AW13: 0 | AX13: 0
... A251: FALSE | B251: 9 - KROMA GESTAO E SERVICOS EM ENERGIA ELETRICA | C251: 12104 | D251: Lançamento Contábil Manual | E251: 10497 | F251: C02408 | G251: FENIX RESIDUOS | H251: 200.67 | I251: FENIX GERENCIAMENTO DE RESIDUOS LTDA | J251: 74077983000109 | K251: 0 | L251: 200.67 | M251: 0 | N251: 0 | O251: 200.67 | P251: 200.67 | Q251: R$ | R251: 0 | S251: 0 | T251: 0 | U251: 0 | V251: 46203 | W251: 46142 | X251: 174 | Y251: VLR REF SRV GESTAO NF 1276 FENIX RESIDUOS | AE251: Não Informado | AF251: Não Informado | AL251: 0 | AQ251: 0 | AR251: 0 | AS251: 0 | AT251: 0 | AU251: 0 | AV251: 0 | AW251: 0 | AX251: 0
M252: =SUBTOTAL(9,M2:M251) -> 0 | N252: =SUBTOTAL(9,N2:N251) -> 0 | O252: =SUBTOTAL(9,O2:O251) -> 4925 | P252: =SUBTOTAL(9,P2:P251) -> 4925 | AL252: =SUBTOTAL(9,AL2:AL251) -> 0 | AQ252: =SUBTOTAL(9,AQ2:AQ251) -> 0 | AS252: =SUBTOTAL(9,AS2:AS251) -> 0 | AT252: =SUBTOTAL(9,AT2:AT251) -> 0 | AV252: =SUBTOTAL(9,AV2:AV251) -> 0 | AX252: =SUBTOTAL(9,AX2:AX251) -> 0

Sheet CADASTRO CLIENTE
A1: Nome do PN | B1: Código do PN | C1: Nome Fantasia | D1: CPF/CNPJ | E1: Saldo da conta
A2: 1 OFICIO DE NOTAS DO RECIFE | B2: F06107 | E2: 0
A3: 1 TABELIONATO DE PROTESTO DA COMARCA DE | B3: F04857 | C3: 1 TABELIONATO DE PROTESTO DO RECIFE | D3: 28.993.451/0001-96 | E3: 0
A4: 1 TABELIONATO DE PROTESTO DO RECIFE | B4: F04638 | C4: 1 TABELIONATO DE PROTESTO DO RECIFE | D4: 52.945.080/0001-51 | E4: 0
A5: 1, 2, 3 MARKETING DE EVENTOS LTDA | B5: F04335 | C5: 1, 2, 3 MARKETING DE EVENTOS LTDA | D5: 10.414.014/0001-05 | E5: 0
A6: 1. SERVICO NOTARIAL E DE REGISTROS | B6: F04722 | C6: CARTORIO ANTONIA DE CAMPOS MACIEL | D6: 00.964.635/0001-09 | E6: 0
A7: 1001 INFORMATICA 1001 SOLUCOES EM INFORM | B7: F03187 | C7: 1001 INFORMATICA 100 | D7: 40.873.358/0001-43 | E7: 0
A8: 11 SUPERINTENDENCIA DE POLICIA RODOVIARI | B8: F03513 | C8: 11 SUPERINTENDENCIA | D8: 00.394.494/0108-75 | E8: 0
A9: 2 OFICIO DE REG DE TITULOS DOC E CIVIL | B9: F04587 | C9: 2 OFICIO DE REG DE TITULOS DOC E CIVIL | D9: 41.322.339/0001-91 | E9: 0
A10: 2.0 HOTEIS BOA VISTA | B10: F04102 | C10: 2.0 HOTEIS BOA VISTA | D10: 17.505.303/0001-69 | E10: 0
A11: 2PAR GESTAO EM NEGOCIOS S/S LTDA | B11: F03416 | C11: 2PAR GESTAO EM NEGO | D11: 18.071.838/0001-31 | E11: 0
A12: 2W ECOBANK S.A. | B12: C01279 | C12: 2W ENERGIA | D12: 8773135000100 | E12: 0
A13: 2W ECOBANK S.A. | B13: F01332 | C13: 2W ENERGIA | D13: 8773135000100 | E13: 0
A14: 2º REGISTRO DE TITULOS E DOC E REG CIVIL | B14: F05285 | C14: 2º REGISTRO DE TITULOS E DOCUMENTOS E RE | D14: 54.813.099/0001-70 | E14: 0
A15: 2º TABELIONATO DE NOTAS E OFICIO DE REGI | B15: F05267 | C15: 2º TABELIONATO DE NOTAS E OFICIO DE REGI | D15: 05.614.888/0001-76 | E15: 0
A16: 3 ON COMERCIO E SERV EM TEC EIRELI | B16: F05274 | C16: 3 ON COMERCIO E SERV EM TEC EIRELI | D16: 31.924.265/0001-00 | E16: 0
A17: 3 TABELIONATO DE PROTESTO DE RECIFE | B17: F04855 | C17: 3 TABELIONATO DE PROTESTO DE RECIFE | D17: 29.640.584/0001-41 | E17: 0
A18: 3 TABELIONATO DE PROTESTO DE TITULOS E D | B18: F04517 | C18: 3 TABELIONATO DE PROTESTO DE TITULOS E D | D18: 30.672.081/0001-37 | E18: 0
A19: 3 TABELIONATO NOTAS PROTESTO TITULOS REG | B19: F04625 | C19: CARTORIO FRANCISCO XIMENES DE MELO | D19: 01.730.807/0001-42 | E19: 0
A20: 3A MINING S.A. | B20: C02871 | C20: 3A MINING | D20: 14482711000235 | E20: 0
A21: 3A MINING S.A. | B21: F01578 | C21: 3A MINING | D21: 14482711000235 | E21: 0
A22: 3G - TERCEIRA GERACAO COMERCIALIZADORA DE ENERGIA LTDA | B22: C01306 | C22: 3G COMERCIALIZADORA | D22: 17838938000188 | E22: 0
A23: 3G - TERCEIRA GERACAO COMERCIALIZADORA DE ENERGIA LTDA | B23: F01997 | C23: 3G COMERCIALIZADORA | D23: 17838938000188 | E23: 0
A24: 3R EMPREENDIMENTOS R A CASTRO DOS SANTOS | B24: F03514 | C24: 3R EMPREENDIMENTOS R | D24: 15.012.245/0001-06 | E24: 0
A25: 3RIOS FIBRAS E RESINAS LTDA | B25: C01572 | C25: 3RIOS | D25: 29928004000116 | E25: 0
A26: 3RIOS FIBRAS E RESINAS LTDA | B26: F02234 | C26: 3RIOS | D26: 29928004000116 | E26: 0
A27: 3TEC LTDA | B27: F05006 | C27: 3TEC LTDA ETIQUETAS E PLAQUETAS | D27: 00.329.754/0001-90 | E27: 0
A28: 4 TABELIONATO DE PROTESTO DE RECIFE | B28: F04878 | C28: 4 TABELIONATO DE PROTESTO DE RECIFE | D28: 28.922.067/0001-00 | E28: 0
A29: 4A DIVISAO - INDUSTRIA E COMERCIO DE MOVEIS LTDA | B29: C02669 | C29: QUARTA DIVISAO | D29: 66550492000105 | E29: 0
A30: 4A DIVISAO - INDUSTRIA E COMERCIO DE MOVEIS LTDA | B30: F03122 | C30: QUARTA DIVISAO | D30: 66550492000105 | E30: 0
A31: 4M - TREINAMENTOS EMPRESARIAIS E ASSESSO | B31: F04108 | C31: 4M - TREINAMENTOS | D31: 06.556.167/0001-10 | E31: 0
A32: 50.826.642 EMANUELA BEZERRA JESSE | B32: F05043 | C32: EMANUELA B JESSE | D32: 50.826.642/0001-12 | E32: 0
A33: 53.653.386 EDUARDO COSTA CUNHA | B33: F05417 | C33: 53.653.386 EDUARDO COSTA CUNHA | D33: 53.653.386/0001-05 | E33: 0
A34: 59.426.154 HITALLO JEAN DE HOLANDA FREIT | B34: F05424 | C34: 59.426.154 HITALLO JEAN DE HOLANDA FREIT | D34: 59.426.154/0001-92 | E34: 0
A35: 88 ENERGIA S.A. | B35: C00889 | C35: 88 ENERGIA | D35: 28185217000132 | E35: 3230000.2
A36: 88 ENERGIA S.A. | B36: F02353 | C36: 88 ENERGIA | D36: 28185217000132 | E36: 0
A37: A & L DESIGNER SERVICOS E REP. EIRELI | B37: F04229 | C37: A & L DESIGNER SERVICOS E REP. EIRELI | D37: 15.594.950/0001-69 | E37: 0
A38: A A DE CARVALHO SERVICOS DE DESPACHOS EI | B38: F04671 | C38: A A DE CARVALHO SERVICOS DE DESPACHOS EI | D38: 23.352.218/0001-00 | E38: 0
A39: A BATISTA DOS SANTOS COMERCIO | B39: F04110 | C39: FLORICULTURA PARK DAS FLORES | D39: 18.738.113/0001-54 | E39: 0
A40: A DE M MARTINS ALVES | B40: F05635 | C40: A DE M MARTINS ALVES | D40: 13.767.337/0001-70 | E40: 0
A41: A EURAN DE CARVALHO | B41: F05427 | C41: A EURAN DE CARVALHO | D41: 07.121.916/0001-49 | E41: 0
A42: A FARIAS LIMA CONSTRUCOES ME | B42: F05685 | C42: A FARIAS LIMA COSNTRUCOES ME | D42: 10.882.297/0001-10 | E42: 0
A43: A J DA C R FIGUEIREDO SERVICOS | B43: F05580 | C43: A J DA C R FIGUEIREDO SERVICOS | D43: 33.903.310/0001-75 | E43: 0
A44: A K M BARBOSA LOCACOES | B44: F04050 | C44: CROMA SOLUCOES DIGITAIS | D44: 26.038.446/0001-07 | E44: 0
A45: A M CARGAS LOGISTICA LTDA | B45: C01710 | C45: AM CARGAS | D45: 8517838000169 | E45: 0
A46: A M CARGAS LOGISTICA LTDA | B46: F01067 | C46: AM CARGAS | D46: 8517838000169 | E46: 0
A47: A M D BATISTA IND E COMERC EIRELI | B47: F04512 | C47: A M D BATISTA IND E COMERC EIRELI | D47: 13.229.781/0007-28 | E47: 0
A48: A M S DE MEDEIROS - EPP | B48: F04749 | C48: INFORCENTER | D48: 07.419.783/0001-91 | E48: 0
A49: A OLIVEIRA DOS SANTOS - LATICINIOS | B49: C02142 | C49: A OLIVEIRA DOS SANTOS - LATICINIOS | D49: 22910261000181 | E49: 0
A50: A OLIVEIRA DOS SANTOS - LATICINIOS | B50: F02098 | C50: A OLIVEIRA DOS SANTOS - LATICINIOS | D50: 22910261000181 | E50: 0
A51: A R DA SILVA EIRELI | B51: C00864 | C51: NOROESTE VIDROS | D51: 7129558000110 | E51: 0
A52: A R DA SILVA EIRELI | B52: F00994 | C52: NOROESTE VIDROS | D52: 7129558000110 | E52: 0
A53: A SAMAMBAIA COMERCIO E SERVICOS DE PLANT | B53: F04091 | C53: A SAMAMBAIA COMERCIO E SERVICOS DE PLANT | D53: 13.919.456/0001-00 | E53: 0
A54: A. C. D. A. IMPORTACAO E EXPORTACAO LTDA | B54: C00001 | C54: ARAUJO TANGARA | D54: 84308980000346 | E54: 0
A55: A. C. D. A. IMPORTACAO E EXPORTACAO LTDA | B55: C00002 | C55: ARAUJO RIO DE JANEIRO | D55: 84308980000699 | E55: 0
A56: A. C. D. A. IMPORTACAO E EXPORTACAO LTDA | B56: C00003 | C56: ARAUJO CHICO MENDES | D56: 84308980000770 | E56: 0
A57: A. C. D. A. IMPORTACAO E EXPORTACAO LTDA | B57: C00004 | C57: ARAUJO BOSQUE | D57: 84308980000184 | E57: 0
A58: A. C. D. A. IMPORTACAO E EXPORTACAO LTDA | B58: C00005 | C58: ARAUJO AVIARIO | D58: 84308980000508 | E58: 0
A59: A. C. D. A. IMPORTACAO E EXPORTACAO LTDA | B59: C00352 | C59: ARAUJO PORTO VELHO | D59: 84308980000931 | E59: 0
A60: A. C. D. A. IMPORTACAO E EXPORTACAO LTDA | B60: C00655 | C60: ARAUJO CD | D60: 84308980000850 | E60: 0
A61: A. C. D. A. IMPORTACAO E EXPORTACAO LTDA | B61: C00656 | C61: ARAUJO SOBRAL | D61: 84308980001660 | E61: 0
A62: A. C. D. A. IMPORTACAO E EXPORTACAO LTDA | B62: C00657 | C62: ARAUJO MIX | D62: 84308980001407 | E62: 0
A63: A. C. D. A. IMPORTACAO E EXPORTACAO LTDA | B63: C00658 | C63: ARAUJO PLACAS | D63: 84308980001741 | E63: 0
A64: A. C. D. A. IMPORTACAO E EXPORTACAO LTDA | B64: C00659 | C64: ARAUJO AMAPA | D64: 84308980001237 | E64: 0
A65: A. C. D. A. IMPORTACAO E EXPORTACAO LTDA | B65: F02759 | C65: ARAUJO PLACAS | D65: 84308980001741 | E65: 0
... A77: A. CONTATO - INDUSTRIA CERAMICA | B77: F01163 | C77: CERAMICA PLANALTO | D77: 9278199000199 | E77: 0
A78: A. R. BARBOSA FILHO | B78: F03798 | C78: GRUPO LIDERANCA TERCERIZACAO | D78: 21.765.518/0001-96 | E78: 0
A79: A. R. HENRIQUES LAZER E RECREACAO LTDA | B79: F05103 | C79: A. R. HENRIQUES LAZER E RECREACAO LTDA | D79: 11.103.976/0001-06 | E79: 0
A80: A.J.J. EMPRESA DE ALIMENTOS LTDA | B80: C01680 | C80: AJJ ALIMENTOS | D80: 8071185000137 | E80: 1072.03
A81: A.J.J. EMPRESA DE ALIMENTOS LTDA | B81: F01045 | C81: AJJ ALIMENTOS | D81: 8071185000137 | E81: 0
A82: A.M COMBUSTIVEIS E LUBRIFICANTES LTDA | B82: F05442 | C82: A.M COMBUSTIVEIS E LUBRIFICANTES LTDA | D82: 39.612.865/0001-44 | E82: 0
A83: A.W. FABER CASTELL S.A. | B83: C00559 | C83: FABER CASTELL | D83: 59596908000748 | E83: 0
A84: A.W. FABER CASTELL S.A. | B84: F03148 | C84: FABER CASTELL | D84: 59596908000748 | E84: 0
A85: ABATEDOURO DE AVES CALIFORNIA LTDA | B85: C01212 | C85: FRANGO GONZALEZ FILIAL | D85: 65790610000262 | E85: 0
A86: ABATEDOURO DE AVES CALIFORNIA LTDA | B86: C01213 | C86: FRANGO GONZALEZ | D86: 65790610000181 | E86: 0
A87: ABATEDOURO DE AVES CALIFORNIA LTDA | B87: F03118 | C87: FRANGO GONZALEZ FILIAL | D87: 65790610000262 | E87: 0
A88: ABATEDOURO DE AVES CALIFORNIA LTDA | B88: F03119 | C88: FRANGO GONZALEZ | D88: 65790610000181 | E88: 0
A89: ABB ELETRIFICACAO | B89: F05624 | C89: ABB ELETRIFICACAO | D89: 33.449.988/0001-20 | E89: 0
A90: ABBOTT LABORATORIOS DO BRASIL LTDA | B90: C02563 | C90: ABBOTT | D90: 56998701001279 | E90: 0
A91: ABBOTT LABORATORIOS DO BRASIL LTDA | B91: F02923 | C91: ABBOTT | D91: 56998701001279 | E91: 0
A92: ABC BRASIL COMERCIALIZADORA DE ENERGIA LTDA. | B92: C02013 | C92: ABC BRASIL | D92: 29198324000168 | E92: 554400
A93: ABC BRASIL COMERCIALIZADORA DE ENERGIA LTDA. | B93: F02719 | C93: ABC BRASIL | D93: 29198324000168 | E93: -2652802.4
A94: ABENAIAS JOSE DA SILVA | B94: C03279 | C94: ABENAIAS JOSE DA SILVA | D94: 314.196.018-65 | E94: 0
A95: ABENAIAS JOSE DA SILVA | B95: F03371 | C95: ABENAIAS JOSE DA SIL | D95: 314.196.018-65 | E95: 0
A96: ABES - SOCIEDADE BAIANA DE ENSINO SUPERIOR LTDA | B96: C01378 | C96: SER - ABES PITUBA | D96: 32697294000653 | E96: 0
A97: ABES - SOCIEDADE BAIANA DE ENSINO SUPERIOR LTDA | B97: C01379 | C97: SER - ABES PITUBA - MATRIZ | D97: 32697294000149 | E97: 0
A98: ABES - SOCIEDADE BAIANA DE ENSINO SUPERIOR LTDA | B98: F02089 | C98: SER - ABES PITUBA | D98: 32697294000653 | E98: 0
A99: ABES - SOCIEDADE BAIANA DE ENSINO SUPERIOR LTDA | B99: F02090 | C99: SER - ABES PITUBA - MATRIZ | D99: 32697294000149 | E99: 0
A100: ABRACEEL ASSOCIACAO BRASILEIRA DOS COMER | B100: F03198 | C100: ABRACEEL ASSOCIACAO | D100: 03.701.689/0001-70 | E100: -8190
A101: ABRANJO GERACAO DE ENERGIA S/A | B101: C00361 | C101: ABRANJO GERACAO | D101: 13562900000174 | E101: 0
A102: ABRANJO GERACAO DE ENERGIA S/A | B102: F01847 | C102: ABRANJO GERACAO | D102: 13562900000174 | E102: 0
A103: ABRANTES e SARMENTO LTDA | B103: C02905 | C103: ABRANTES e SARMENTO | D103: 11179771000104 | E103: 0
A104: ABRANTES e SARMENTO LTDA | B104: F01612 | C104: ABRANTES e SARMENTO | D104: 11179771000104 | E104: 0
A105: ABRAPCH ASSOCIACAO BRASILEIRA DE FOMENTO | B105: F03498 | C105: ABRAPCH ASSOCIACAO B | D105: 18.241.195/0001-27 | E105: 0
A106: ABRASEL - PE | B106: F05226 | C106: ABRASEL - PE | D106: 35.327.857/0001-03 | E106: 0
A107: ABRASEL CE | B107: F05271 | C107: ABRASEL CE | D107: 41.655.291/0001-33 | E107: 0
A108: ABREU E LIMA LOGISTICA, ARMAZENAGEM, TRANSPORTES E DISTRIBUICAO LTDA | B108: C01637 | C108: ABLOG | D108: 8057729000106 | E108: 0
A109: ABREU E LIMA LOGISTICA, ARMAZENAGEM, TRANSPORTES E DISTRIBUICAO LTDA | B109: F01022 | C109: ABLOG | D109: 8057729000106 | E109: 0
A110: AC MORAIS COMBUSTIVEIS LTDA | B110: C01746 | C110: AC MORAIS | D110: 22493813000101 | E110: 1679.16
A111: AC MORAIS COMBUSTIVEIS LTDA | B111: F01701 | C111: AC MORAIS | D111: 22493813000101 | E111: 0
...
